[{"path":"src/main/java/duke/Deadline.java","fileType":"java","lines":[{"lineNumber":1,"author":{"gitId":"waynetee"},"content":"package duke;","lastModifiedDate":"2021-08-21"},{"lineNumber":2,"author":{"gitId":"waynetee"},"content":"","lastModifiedDate":"2021-08-21"},{"lineNumber":3,"author":{"gitId":"waynetee"},"content":"import java.time.LocalDateTime;","lastModifiedDate":"2021-08-21"},{"lineNumber":4,"author":{"gitId":"waynetee"},"content":"import java.time.format.DateTimeFormatter;","lastModifiedDate":"2021-08-21"},{"lineNumber":5,"author":{"gitId":"waynetee"},"content":"","lastModifiedDate":"2021-08-21"},{"lineNumber":6,"author":{"gitId":"waynetee"},"content":"public class Deadline extends Task {","lastModifiedDate":"2021-08-14"},{"lineNumber":7,"author":{"gitId":"waynetee"},"content":"    static final DateTimeFormatter formatter \u003d DateTimeFormatter.ofPattern(\"EEE, d MMM yyyy hh:mma\");","lastModifiedDate":"2021-08-21"},{"lineNumber":8,"author":{"gitId":"waynetee"},"content":"    LocalDateTime time;","lastModifiedDate":"2021-08-21"},{"lineNumber":9,"author":{"gitId":"waynetee"},"content":"","lastModifiedDate":"2021-08-14"},{"lineNumber":10,"author":{"gitId":"waynetee"},"content":"    public Deadline(String description, LocalDateTime time) {","lastModifiedDate":"2021-08-21"},{"lineNumber":11,"author":{"gitId":"waynetee"},"content":"        this.description \u003d description;","lastModifiedDate":"2021-08-14"},{"lineNumber":12,"author":{"gitId":"waynetee"},"content":"        this.time \u003d time;","lastModifiedDate":"2021-08-14"},{"lineNumber":13,"author":{"gitId":"waynetee"},"content":"    }","lastModifiedDate":"2021-08-14"},{"lineNumber":14,"author":{"gitId":"waynetee"},"content":"","lastModifiedDate":"2021-08-14"},{"lineNumber":15,"author":{"gitId":"waynetee"},"content":"    @Override","lastModifiedDate":"2021-08-14"},{"lineNumber":16,"author":{"gitId":"waynetee"},"content":"    public String toString() {","lastModifiedDate":"2021-08-14"},{"lineNumber":17,"author":{"gitId":"waynetee"},"content":"        return String.format(\"[D][%c] %s (by: %s)\", isDone ? \u0027X\u0027 : \u0027 \u0027, description, time.format(formatter));","lastModifiedDate":"2021-08-21"},{"lineNumber":18,"author":{"gitId":"waynetee"},"content":"    }","lastModifiedDate":"2021-08-14"},{"lineNumber":19,"author":{"gitId":"waynetee"},"content":"}","lastModifiedDate":"2021-08-14"}],"authorContributionMap":{"waynetee":19}},{"path":"src/main/java/duke/Duke.java","fileType":"java","lines":[{"lineNumber":1,"author":{"gitId":"waynetee"},"content":"package duke;","lastModifiedDate":"2021-08-21"},{"lineNumber":2,"author":{"gitId":"waynetee"},"content":"","lastModifiedDate":"2021-08-21"},{"lineNumber":3,"author":{"gitId":"waynetee"},"content":"import java.io.IOException;","lastModifiedDate":"2021-08-21"},{"lineNumber":4,"author":{"gitId":"waynetee"},"content":"","lastModifiedDate":"2021-08-14"},{"lineNumber":5,"author":{"gitId":"-"},"content":"public class Duke {","lastModifiedDate":"2019-07-29"},{"lineNumber":6,"author":{"gitId":"waynetee"},"content":"    static TaskList tasks \u003d new TaskList();","lastModifiedDate":"2021-08-21"},{"lineNumber":7,"author":{"gitId":"waynetee"},"content":"    static Parser parser \u003d new Parser(tasks);","lastModifiedDate":"2021-08-21"},{"lineNumber":8,"author":{"gitId":"waynetee"},"content":"    static Storage storage;","lastModifiedDate":"2021-08-21"},{"lineNumber":9,"author":{"gitId":"waynetee"},"content":"","lastModifiedDate":"2021-08-14"},{"lineNumber":10,"author":{"gitId":"-"},"content":"    public static void main(String[] args) {","lastModifiedDate":"2019-07-29"},{"lineNumber":11,"author":{"gitId":"waynetee"},"content":"        Ui.show(\"Hello! I\u0027m Duke\", \"What can I do for you?\");","lastModifiedDate":"2021-08-21"},{"lineNumber":12,"author":{"gitId":"waynetee"},"content":"        loadStorage();","lastModifiedDate":"2021-08-21"},{"lineNumber":13,"author":{"gitId":"waynetee"},"content":"        while (true) {","lastModifiedDate":"2021-08-14"},{"lineNumber":14,"author":{"gitId":"waynetee"},"content":"            try {","lastModifiedDate":"2021-08-14"},{"lineNumber":15,"author":{"gitId":"waynetee"},"content":"                String command \u003d Ui.nextLine();","lastModifiedDate":"2021-08-21"},{"lineNumber":16,"author":{"gitId":"waynetee"},"content":"                if (parser.isExit(command)) {","lastModifiedDate":"2021-08-21"},{"lineNumber":17,"author":{"gitId":"waynetee"},"content":"                    Ui.show(\"Bye. Hope to see you again soon!\");","lastModifiedDate":"2021-08-21"},{"lineNumber":18,"author":{"gitId":"waynetee"},"content":"                    storage.close();","lastModifiedDate":"2021-08-21"},{"lineNumber":19,"author":{"gitId":"waynetee"},"content":"                    return;","lastModifiedDate":"2021-08-14"},{"lineNumber":20,"author":{"gitId":"waynetee"},"content":"                } else {","lastModifiedDate":"2021-08-14"},{"lineNumber":21,"author":{"gitId":"waynetee"},"content":"                    Ui.show(parser.parse(command));","lastModifiedDate":"2021-08-21"},{"lineNumber":22,"author":{"gitId":"waynetee"},"content":"                }","lastModifiedDate":"2021-08-14"},{"lineNumber":23,"author":{"gitId":"waynetee"},"content":"                storage.write(command);","lastModifiedDate":"2021-08-21"},{"lineNumber":24,"author":{"gitId":"waynetee"},"content":"            } catch (Exception e) {","lastModifiedDate":"2021-08-14"},{"lineNumber":25,"author":{"gitId":"waynetee"},"content":"                Ui.show(e.getMessage());","lastModifiedDate":"2021-08-21"},{"lineNumber":26,"author":{"gitId":"waynetee"},"content":"            }","lastModifiedDate":"2021-08-14"},{"lineNumber":27,"author":{"gitId":"waynetee"},"content":"        }","lastModifiedDate":"2021-08-14"},{"lineNumber":28,"author":{"gitId":"-"},"content":"    }","lastModifiedDate":"2019-07-29"},{"lineNumber":29,"author":{"gitId":"waynetee"},"content":"","lastModifiedDate":"2021-08-14"},{"lineNumber":30,"author":{"gitId":"waynetee"},"content":"    static void loadStorage() {","lastModifiedDate":"2021-08-21"},{"lineNumber":31,"author":{"gitId":"waynetee"},"content":"        try {","lastModifiedDate":"2021-08-21"},{"lineNumber":32,"author":{"gitId":"waynetee"},"content":"            storage \u003d new Storage(\"duke.txt\");","lastModifiedDate":"2021-08-21"},{"lineNumber":33,"author":{"gitId":"waynetee"},"content":"            for (String command : storage.readAllLines())","lastModifiedDate":"2021-08-21"},{"lineNumber":34,"author":{"gitId":"waynetee"},"content":"                parser.parse(command);","lastModifiedDate":"2021-08-21"},{"lineNumber":35,"author":{"gitId":"waynetee"},"content":"        } catch (IOException | DukeException e) {","lastModifiedDate":"2021-08-21"},{"lineNumber":36,"author":{"gitId":"waynetee"},"content":"            e.printStackTrace();","lastModifiedDate":"2021-08-21"},{"lineNumber":37,"author":{"gitId":"waynetee"},"content":"        }","lastModifiedDate":"2021-08-21"},{"lineNumber":38,"author":{"gitId":"waynetee"},"content":"    }","lastModifiedDate":"2021-08-21"},{"lineNumber":39,"author":{"gitId":"-"},"content":"}","lastModifiedDate":"2019-07-29"}],"authorContributionMap":{"-":4,"waynetee":35}},{"path":"src/main/java/duke/DukeException.java","fileType":"java","lines":[{"lineNumber":1,"author":{"gitId":"waynetee"},"content":"package duke;","lastModifiedDate":"2021-08-21"},{"lineNumber":2,"author":{"gitId":"waynetee"},"content":"","lastModifiedDate":"2021-08-21"},{"lineNumber":3,"author":{"gitId":"waynetee"},"content":"public class DukeException extends Exception {","lastModifiedDate":"2021-08-14"},{"lineNumber":4,"author":{"gitId":"waynetee"},"content":"    DukeException(String message) {","lastModifiedDate":"2021-08-14"},{"lineNumber":5,"author":{"gitId":"waynetee"},"content":"        super(message);","lastModifiedDate":"2021-08-14"},{"lineNumber":6,"author":{"gitId":"waynetee"},"content":"    }","lastModifiedDate":"2021-08-14"},{"lineNumber":7,"author":{"gitId":"waynetee"},"content":"}","lastModifiedDate":"2021-08-14"}],"authorContributionMap":{"waynetee":7}},{"path":"src/main/java/duke/Event.java","fileType":"java","lines":[{"lineNumber":1,"author":{"gitId":"waynetee"},"content":"package duke;","lastModifiedDate":"2021-08-21"},{"lineNumber":2,"author":{"gitId":"waynetee"},"content":"","lastModifiedDate":"2021-08-21"},{"lineNumber":3,"author":{"gitId":"waynetee"},"content":"import java.time.LocalDateTime;","lastModifiedDate":"2021-08-21"},{"lineNumber":4,"author":{"gitId":"waynetee"},"content":"import java.time.format.DateTimeFormatter;","lastModifiedDate":"2021-08-21"},{"lineNumber":5,"author":{"gitId":"waynetee"},"content":"","lastModifiedDate":"2021-08-21"},{"lineNumber":6,"author":{"gitId":"waynetee"},"content":"public class Event extends Task {","lastModifiedDate":"2021-08-14"},{"lineNumber":7,"author":{"gitId":"waynetee"},"content":"    static final DateTimeFormatter formatter \u003d DateTimeFormatter.ofPattern(\"EEE, d MMM yyyy hh:mma\");","lastModifiedDate":"2021-08-21"},{"lineNumber":8,"author":{"gitId":"waynetee"},"content":"    LocalDateTime time;","lastModifiedDate":"2021-08-21"},{"lineNumber":9,"author":{"gitId":"waynetee"},"content":"","lastModifiedDate":"2021-08-14"},{"lineNumber":10,"author":{"gitId":"waynetee"},"content":"    public Event(String description, LocalDateTime time) {","lastModifiedDate":"2021-08-21"},{"lineNumber":11,"author":{"gitId":"waynetee"},"content":"        this.description \u003d description;","lastModifiedDate":"2021-08-14"},{"lineNumber":12,"author":{"gitId":"waynetee"},"content":"        this.time \u003d time;","lastModifiedDate":"2021-08-14"},{"lineNumber":13,"author":{"gitId":"waynetee"},"content":"    }","lastModifiedDate":"2021-08-14"},{"lineNumber":14,"author":{"gitId":"waynetee"},"content":"","lastModifiedDate":"2021-08-14"},{"lineNumber":15,"author":{"gitId":"waynetee"},"content":"    @Override","lastModifiedDate":"2021-08-14"},{"lineNumber":16,"author":{"gitId":"waynetee"},"content":"    public String toString() {","lastModifiedDate":"2021-08-14"},{"lineNumber":17,"author":{"gitId":"waynetee"},"content":"        return String.format(\"[E][%c] %s (at: %s)\", isDone ? \u0027X\u0027 : \u0027 \u0027, description, time.format(formatter));","lastModifiedDate":"2021-08-21"},{"lineNumber":18,"author":{"gitId":"waynetee"},"content":"    }","lastModifiedDate":"2021-08-14"},{"lineNumber":19,"author":{"gitId":"waynetee"},"content":"}","lastModifiedDate":"2021-08-14"}],"authorContributionMap":{"waynetee":19}},{"path":"src/main/java/duke/Parser.java","fileType":"java","lines":[{"lineNumber":1,"author":{"gitId":"waynetee"},"content":"package duke;","lastModifiedDate":"2021-08-21"},{"lineNumber":2,"author":{"gitId":"waynetee"},"content":"","lastModifiedDate":"2021-08-21"},{"lineNumber":3,"author":{"gitId":"waynetee"},"content":"import java.time.LocalDateTime;","lastModifiedDate":"2021-08-21"},{"lineNumber":4,"author":{"gitId":"waynetee"},"content":"import java.time.format.DateTimeFormatter;","lastModifiedDate":"2021-08-21"},{"lineNumber":5,"author":{"gitId":"waynetee"},"content":"import java.util.ArrayList;","lastModifiedDate":"2021-08-21"},{"lineNumber":6,"author":{"gitId":"waynetee"},"content":"import java.util.List;","lastModifiedDate":"2021-08-21"},{"lineNumber":7,"author":{"gitId":"waynetee"},"content":"","lastModifiedDate":"2021-08-21"},{"lineNumber":8,"author":{"gitId":"waynetee"},"content":"public class Parser {","lastModifiedDate":"2021-08-21"},{"lineNumber":9,"author":{"gitId":"waynetee"},"content":"    TaskList tasks;","lastModifiedDate":"2021-08-21"},{"lineNumber":10,"author":{"gitId":"waynetee"},"content":"","lastModifiedDate":"2021-08-21"},{"lineNumber":11,"author":{"gitId":"waynetee"},"content":"    Parser(TaskList taskList) {","lastModifiedDate":"2021-08-21"},{"lineNumber":12,"author":{"gitId":"waynetee"},"content":"        tasks \u003d taskList;","lastModifiedDate":"2021-08-21"},{"lineNumber":13,"author":{"gitId":"waynetee"},"content":"    }","lastModifiedDate":"2021-08-21"},{"lineNumber":14,"author":{"gitId":"waynetee"},"content":"","lastModifiedDate":"2021-08-21"},{"lineNumber":15,"author":{"gitId":"waynetee"},"content":"    boolean isExit(String input) {","lastModifiedDate":"2021-08-21"},{"lineNumber":16,"author":{"gitId":"waynetee"},"content":"        return input.equals(\"bye\");","lastModifiedDate":"2021-08-21"},{"lineNumber":17,"author":{"gitId":"waynetee"},"content":"    }","lastModifiedDate":"2021-08-21"},{"lineNumber":18,"author":{"gitId":"waynetee"},"content":"","lastModifiedDate":"2021-08-21"},{"lineNumber":19,"author":{"gitId":"waynetee"},"content":"    String[] parse(String input) throws DukeException {","lastModifiedDate":"2021-08-21"},{"lineNumber":20,"author":{"gitId":"waynetee"},"content":"        if (input.equals(\"list\")) {","lastModifiedDate":"2021-08-21"},{"lineNumber":21,"author":{"gitId":"waynetee"},"content":"            return list();","lastModifiedDate":"2021-08-21"},{"lineNumber":22,"author":{"gitId":"waynetee"},"content":"        } else if (input.startsWith(\"done\")) {","lastModifiedDate":"2021-08-21"},{"lineNumber":23,"author":{"gitId":"waynetee"},"content":"            return done(input);","lastModifiedDate":"2021-08-21"},{"lineNumber":24,"author":{"gitId":"waynetee"},"content":"        } else if (input.startsWith(\"delete\")) {","lastModifiedDate":"2021-08-21"},{"lineNumber":25,"author":{"gitId":"waynetee"},"content":"            return delete(input);","lastModifiedDate":"2021-08-21"},{"lineNumber":26,"author":{"gitId":"waynetee"},"content":"        } else {","lastModifiedDate":"2021-08-21"},{"lineNumber":27,"author":{"gitId":"waynetee"},"content":"            return addTask(input);","lastModifiedDate":"2021-08-21"},{"lineNumber":28,"author":{"gitId":"waynetee"},"content":"        }","lastModifiedDate":"2021-08-21"},{"lineNumber":29,"author":{"gitId":"waynetee"},"content":"    }","lastModifiedDate":"2021-08-21"},{"lineNumber":30,"author":{"gitId":"waynetee"},"content":"","lastModifiedDate":"2021-08-21"},{"lineNumber":31,"author":{"gitId":"waynetee"},"content":"    String[] list() {","lastModifiedDate":"2021-08-21"},{"lineNumber":32,"author":{"gitId":"waynetee"},"content":"        List\u003cString\u003e out \u003d new ArrayList\u003c\u003e();","lastModifiedDate":"2021-08-21"},{"lineNumber":33,"author":{"gitId":"waynetee"},"content":"        out.add(\"Here are the tasks in your list:\");","lastModifiedDate":"2021-08-21"},{"lineNumber":34,"author":{"gitId":"waynetee"},"content":"        for (int i \u003d 0; i \u003c tasks.size(); i++) {","lastModifiedDate":"2021-08-21"},{"lineNumber":35,"author":{"gitId":"waynetee"},"content":"            out.add(String.format(\"%d.%s\", i + 1, tasks.get(i)));","lastModifiedDate":"2021-08-21"},{"lineNumber":36,"author":{"gitId":"waynetee"},"content":"        }","lastModifiedDate":"2021-08-21"},{"lineNumber":37,"author":{"gitId":"waynetee"},"content":"        return out.toArray(new String[0]);","lastModifiedDate":"2021-08-21"},{"lineNumber":38,"author":{"gitId":"waynetee"},"content":"    }","lastModifiedDate":"2021-08-21"},{"lineNumber":39,"author":{"gitId":"waynetee"},"content":"","lastModifiedDate":"2021-08-21"},{"lineNumber":40,"author":{"gitId":"waynetee"},"content":"    String[] done(String input) {","lastModifiedDate":"2021-08-21"},{"lineNumber":41,"author":{"gitId":"waynetee"},"content":"        int ind \u003d Integer.parseInt(input.split(\" \", 2)[1]);","lastModifiedDate":"2021-08-21"},{"lineNumber":42,"author":{"gitId":"waynetee"},"content":"        Task task \u003d tasks.get(ind - 1);","lastModifiedDate":"2021-08-21"},{"lineNumber":43,"author":{"gitId":"waynetee"},"content":"        task.setDone();","lastModifiedDate":"2021-08-21"},{"lineNumber":44,"author":{"gitId":"waynetee"},"content":"        return new String[]{\"Nice! I\u0027ve marked this task as done:\", \"  \" + task};","lastModifiedDate":"2021-08-21"},{"lineNumber":45,"author":{"gitId":"waynetee"},"content":"    }","lastModifiedDate":"2021-08-21"},{"lineNumber":46,"author":{"gitId":"waynetee"},"content":"","lastModifiedDate":"2021-08-21"},{"lineNumber":47,"author":{"gitId":"waynetee"},"content":"    String[] addTask(String input) throws DukeException {","lastModifiedDate":"2021-08-21"},{"lineNumber":48,"author":{"gitId":"waynetee"},"content":"        Task task \u003d makeTask(input);","lastModifiedDate":"2021-08-21"},{"lineNumber":49,"author":{"gitId":"waynetee"},"content":"        tasks.add(task);","lastModifiedDate":"2021-08-21"},{"lineNumber":50,"author":{"gitId":"waynetee"},"content":"        return new String[]{","lastModifiedDate":"2021-08-21"},{"lineNumber":51,"author":{"gitId":"waynetee"},"content":"                \"Got it. I\u0027ve added this task:\", \"  \" + task, getTasksLeftMsg()};","lastModifiedDate":"2021-08-21"},{"lineNumber":52,"author":{"gitId":"waynetee"},"content":"    }","lastModifiedDate":"2021-08-21"},{"lineNumber":53,"author":{"gitId":"waynetee"},"content":"","lastModifiedDate":"2021-08-21"},{"lineNumber":54,"author":{"gitId":"waynetee"},"content":"    Task makeTask(String input) throws DukeException {","lastModifiedDate":"2021-08-21"},{"lineNumber":55,"author":{"gitId":"waynetee"},"content":"        DateTimeFormatter formatter \u003d DateTimeFormatter.ofPattern(\"d/M/yyyy HHmm\");","lastModifiedDate":"2021-08-21"},{"lineNumber":56,"author":{"gitId":"waynetee"},"content":"        String[] parts \u003d input.split(\" \", 2);","lastModifiedDate":"2021-08-21"},{"lineNumber":57,"author":{"gitId":"waynetee"},"content":"        String type \u003d parts[0];","lastModifiedDate":"2021-08-21"},{"lineNumber":58,"author":{"gitId":"waynetee"},"content":"        switch (type) {","lastModifiedDate":"2021-08-21"},{"lineNumber":59,"author":{"gitId":"waynetee"},"content":"        case \"todo\":","lastModifiedDate":"2021-08-21"},{"lineNumber":60,"author":{"gitId":"waynetee"},"content":"            if (parts.length \u003d\u003d 1) {","lastModifiedDate":"2021-08-21"},{"lineNumber":61,"author":{"gitId":"waynetee"},"content":"                throw new DukeException(\"☹ OOPS!!! The description of a todo cannot be empty.\");","lastModifiedDate":"2021-08-21"},{"lineNumber":62,"author":{"gitId":"waynetee"},"content":"            }","lastModifiedDate":"2021-08-21"},{"lineNumber":63,"author":{"gitId":"waynetee"},"content":"            return new Todo(parts[1]);","lastModifiedDate":"2021-08-21"},{"lineNumber":64,"author":{"gitId":"waynetee"},"content":"        case \"deadline\": {","lastModifiedDate":"2021-08-21"},{"lineNumber":65,"author":{"gitId":"waynetee"},"content":"            String[] subparts \u003d parts[1].split(\" /by \", 2);","lastModifiedDate":"2021-08-21"},{"lineNumber":66,"author":{"gitId":"waynetee"},"content":"            return new Deadline(subparts[0], LocalDateTime.parse(subparts[1], formatter));","lastModifiedDate":"2021-08-21"},{"lineNumber":67,"author":{"gitId":"waynetee"},"content":"        }","lastModifiedDate":"2021-08-21"},{"lineNumber":68,"author":{"gitId":"waynetee"},"content":"        case \"event\": {","lastModifiedDate":"2021-08-21"},{"lineNumber":69,"author":{"gitId":"waynetee"},"content":"            String[] subparts \u003d parts[1].split(\" /at \", 2);","lastModifiedDate":"2021-08-21"},{"lineNumber":70,"author":{"gitId":"waynetee"},"content":"            return new Event(subparts[0], LocalDateTime.parse(subparts[1], formatter));","lastModifiedDate":"2021-08-21"},{"lineNumber":71,"author":{"gitId":"waynetee"},"content":"        }","lastModifiedDate":"2021-08-21"},{"lineNumber":72,"author":{"gitId":"waynetee"},"content":"        default:","lastModifiedDate":"2021-08-21"},{"lineNumber":73,"author":{"gitId":"waynetee"},"content":"            throw new DukeException(\"☹ OOPS!!! I\u0027m sorry, but I don\u0027t know what that means :-(\");","lastModifiedDate":"2021-08-21"},{"lineNumber":74,"author":{"gitId":"waynetee"},"content":"        }","lastModifiedDate":"2021-08-21"},{"lineNumber":75,"author":{"gitId":"waynetee"},"content":"    }","lastModifiedDate":"2021-08-21"},{"lineNumber":76,"author":{"gitId":"waynetee"},"content":"","lastModifiedDate":"2021-08-21"},{"lineNumber":77,"author":{"gitId":"waynetee"},"content":"    String[] delete(String input) {","lastModifiedDate":"2021-08-21"},{"lineNumber":78,"author":{"gitId":"waynetee"},"content":"        int ind \u003d Integer.parseInt(input.split(\" \", 2)[1]);","lastModifiedDate":"2021-08-21"},{"lineNumber":79,"author":{"gitId":"waynetee"},"content":"        Task task \u003d tasks.remove(ind - 1);","lastModifiedDate":"2021-08-21"},{"lineNumber":80,"author":{"gitId":"waynetee"},"content":"        return new String[]{\"Noted. I\u0027ve removed this task:\", \"  \" + task, getTasksLeftMsg()};","lastModifiedDate":"2021-08-21"},{"lineNumber":81,"author":{"gitId":"waynetee"},"content":"    }","lastModifiedDate":"2021-08-21"},{"lineNumber":82,"author":{"gitId":"waynetee"},"content":"","lastModifiedDate":"2021-08-21"},{"lineNumber":83,"author":{"gitId":"waynetee"},"content":"    String getTasksLeftMsg() {","lastModifiedDate":"2021-08-21"},{"lineNumber":84,"author":{"gitId":"waynetee"},"content":"        return String.format(\"Now you have %d %s in the list.\", tasks.size(), tasks.size() \u003d\u003d 1 ? \"task\" : \"tasks\");","lastModifiedDate":"2021-08-21"},{"lineNumber":85,"author":{"gitId":"waynetee"},"content":"    }","lastModifiedDate":"2021-08-21"},{"lineNumber":86,"author":{"gitId":"waynetee"},"content":"}","lastModifiedDate":"2021-08-21"}],"authorContributionMap":{"waynetee":86}},{"path":"src/main/java/duke/Storage.java","fileType":"java","lines":[{"lineNumber":1,"author":{"gitId":"waynetee"},"content":"package duke;","lastModifiedDate":"2021-08-21"},{"lineNumber":2,"author":{"gitId":"waynetee"},"content":"","lastModifiedDate":"2021-08-21"},{"lineNumber":3,"author":{"gitId":"waynetee"},"content":"import java.io.File;","lastModifiedDate":"2021-08-21"},{"lineNumber":4,"author":{"gitId":"waynetee"},"content":"import java.io.FileWriter;","lastModifiedDate":"2021-08-21"},{"lineNumber":5,"author":{"gitId":"waynetee"},"content":"import java.io.IOException;","lastModifiedDate":"2021-08-21"},{"lineNumber":6,"author":{"gitId":"waynetee"},"content":"import java.nio.file.Files;","lastModifiedDate":"2021-08-21"},{"lineNumber":7,"author":{"gitId":"waynetee"},"content":"import java.util.List;","lastModifiedDate":"2021-08-21"},{"lineNumber":8,"author":{"gitId":"waynetee"},"content":"","lastModifiedDate":"2021-08-21"},{"lineNumber":9,"author":{"gitId":"waynetee"},"content":"class Storage {","lastModifiedDate":"2021-08-21"},{"lineNumber":10,"author":{"gitId":"waynetee"},"content":"    private final String filePath;","lastModifiedDate":"2021-08-21"},{"lineNumber":11,"author":{"gitId":"waynetee"},"content":"    private final FileWriter writer;","lastModifiedDate":"2021-08-21"},{"lineNumber":12,"author":{"gitId":"waynetee"},"content":"","lastModifiedDate":"2021-08-21"},{"lineNumber":13,"author":{"gitId":"waynetee"},"content":"    Storage(String filePath) throws IOException {","lastModifiedDate":"2021-08-21"},{"lineNumber":14,"author":{"gitId":"waynetee"},"content":"        this.filePath \u003d filePath;","lastModifiedDate":"2021-08-21"},{"lineNumber":15,"author":{"gitId":"waynetee"},"content":"        writer \u003d new FileWriter(filePath, true);","lastModifiedDate":"2021-08-21"},{"lineNumber":16,"author":{"gitId":"waynetee"},"content":"    }","lastModifiedDate":"2021-08-21"},{"lineNumber":17,"author":{"gitId":"waynetee"},"content":"","lastModifiedDate":"2021-08-21"},{"lineNumber":18,"author":{"gitId":"waynetee"},"content":"    List\u003cString\u003e readAllLines() throws IOException {","lastModifiedDate":"2021-08-21"},{"lineNumber":19,"author":{"gitId":"waynetee"},"content":"        return Files.readAllLines(new File(filePath).toPath());","lastModifiedDate":"2021-08-21"},{"lineNumber":20,"author":{"gitId":"waynetee"},"content":"    }","lastModifiedDate":"2021-08-21"},{"lineNumber":21,"author":{"gitId":"waynetee"},"content":"","lastModifiedDate":"2021-08-21"},{"lineNumber":22,"author":{"gitId":"waynetee"},"content":"    void write(String s) throws IOException {","lastModifiedDate":"2021-08-21"},{"lineNumber":23,"author":{"gitId":"waynetee"},"content":"        writer.write(s + \u0027\\n\u0027);","lastModifiedDate":"2021-08-21"},{"lineNumber":24,"author":{"gitId":"waynetee"},"content":"    }","lastModifiedDate":"2021-08-21"},{"lineNumber":25,"author":{"gitId":"waynetee"},"content":"","lastModifiedDate":"2021-08-21"},{"lineNumber":26,"author":{"gitId":"waynetee"},"content":"    void close() throws IOException {","lastModifiedDate":"2021-08-21"},{"lineNumber":27,"author":{"gitId":"waynetee"},"content":"        writer.close();","lastModifiedDate":"2021-08-21"},{"lineNumber":28,"author":{"gitId":"waynetee"},"content":"    }","lastModifiedDate":"2021-08-21"},{"lineNumber":29,"author":{"gitId":"waynetee"},"content":"}","lastModifiedDate":"2021-08-21"}],"authorContributionMap":{"waynetee":29}},{"path":"src/main/java/duke/Task.java","fileType":"java","lines":[{"lineNumber":1,"author":{"gitId":"waynetee"},"content":"package duke;","lastModifiedDate":"2021-08-21"},{"lineNumber":2,"author":{"gitId":"waynetee"},"content":"","lastModifiedDate":"2021-08-21"},{"lineNumber":3,"author":{"gitId":"waynetee"},"content":"public abstract class Task {","lastModifiedDate":"2021-08-14"},{"lineNumber":4,"author":{"gitId":"waynetee"},"content":"    String description;","lastModifiedDate":"2021-08-14"},{"lineNumber":5,"author":{"gitId":"waynetee"},"content":"    Boolean isDone \u003d false;","lastModifiedDate":"2021-08-14"},{"lineNumber":6,"author":{"gitId":"waynetee"},"content":"","lastModifiedDate":"2021-08-14"},{"lineNumber":7,"author":{"gitId":"waynetee"},"content":"    public void setDone() {","lastModifiedDate":"2021-08-14"},{"lineNumber":8,"author":{"gitId":"waynetee"},"content":"        isDone \u003d true;","lastModifiedDate":"2021-08-14"},{"lineNumber":9,"author":{"gitId":"waynetee"},"content":"    }","lastModifiedDate":"2021-08-14"},{"lineNumber":10,"author":{"gitId":"waynetee"},"content":"}","lastModifiedDate":"2021-08-14"}],"authorContributionMap":{"waynetee":10}},{"path":"src/main/java/duke/TaskList.java","fileType":"java","lines":[{"lineNumber":1,"author":{"gitId":"waynetee"},"content":"package duke;","lastModifiedDate":"2021-08-21"},{"lineNumber":2,"author":{"gitId":"waynetee"},"content":"","lastModifiedDate":"2021-08-21"},{"lineNumber":3,"author":{"gitId":"waynetee"},"content":"import java.util.ArrayList;","lastModifiedDate":"2021-08-21"},{"lineNumber":4,"author":{"gitId":"waynetee"},"content":"","lastModifiedDate":"2021-08-21"},{"lineNumber":5,"author":{"gitId":"waynetee"},"content":"public class TaskList extends ArrayList\u003cTask\u003e {","lastModifiedDate":"2021-08-21"},{"lineNumber":6,"author":{"gitId":"waynetee"},"content":"}","lastModifiedDate":"2021-08-21"}],"authorContributionMap":{"waynetee":6}},{"path":"src/main/java/duke/Todo.java","fileType":"java","lines":[{"lineNumber":1,"author":{"gitId":"waynetee"},"content":"package duke;","lastModifiedDate":"2021-08-21"},{"lineNumber":2,"author":{"gitId":"waynetee"},"content":"","lastModifiedDate":"2021-08-21"},{"lineNumber":3,"author":{"gitId":"waynetee"},"content":"public class Todo extends Task {","lastModifiedDate":"2021-08-14"},{"lineNumber":4,"author":{"gitId":"waynetee"},"content":"    public Todo(String description) {","lastModifiedDate":"2021-08-14"},{"lineNumber":5,"author":{"gitId":"waynetee"},"content":"        this.description \u003d description;","lastModifiedDate":"2021-08-14"},{"lineNumber":6,"author":{"gitId":"waynetee"},"content":"    }","lastModifiedDate":"2021-08-14"},{"lineNumber":7,"author":{"gitId":"waynetee"},"content":"","lastModifiedDate":"2021-08-14"},{"lineNumber":8,"author":{"gitId":"waynetee"},"content":"    @Override","lastModifiedDate":"2021-08-14"},{"lineNumber":9,"author":{"gitId":"waynetee"},"content":"    public String toString() {","lastModifiedDate":"2021-08-14"},{"lineNumber":10,"author":{"gitId":"waynetee"},"content":"        return String.format(\"[T][%c] %s\", isDone ? \u0027X\u0027 : \u0027 \u0027, description);","lastModifiedDate":"2021-08-14"},{"lineNumber":11,"author":{"gitId":"waynetee"},"content":"    }","lastModifiedDate":"2021-08-14"},{"lineNumber":12,"author":{"gitId":"waynetee"},"content":"}","lastModifiedDate":"2021-08-14"}],"authorContributionMap":{"waynetee":12}},{"path":"src/main/java/duke/Ui.java","fileType":"java","lines":[{"lineNumber":1,"author":{"gitId":"waynetee"},"content":"package duke;","lastModifiedDate":"2021-08-21"},{"lineNumber":2,"author":{"gitId":"waynetee"},"content":"","lastModifiedDate":"2021-08-21"},{"lineNumber":3,"author":{"gitId":"waynetee"},"content":"import java.util.Scanner;","lastModifiedDate":"2021-08-21"},{"lineNumber":4,"author":{"gitId":"waynetee"},"content":"","lastModifiedDate":"2021-08-21"},{"lineNumber":5,"author":{"gitId":"waynetee"},"content":"public class Ui {","lastModifiedDate":"2021-08-21"},{"lineNumber":6,"author":{"gitId":"waynetee"},"content":"    static Scanner sc \u003d new Scanner(System.in);","lastModifiedDate":"2021-08-21"},{"lineNumber":7,"author":{"gitId":"waynetee"},"content":"","lastModifiedDate":"2021-08-21"},{"lineNumber":8,"author":{"gitId":"waynetee"},"content":"    static String nextLine() {","lastModifiedDate":"2021-08-21"},{"lineNumber":9,"author":{"gitId":"waynetee"},"content":"        return sc.nextLine();","lastModifiedDate":"2021-08-21"},{"lineNumber":10,"author":{"gitId":"waynetee"},"content":"    }","lastModifiedDate":"2021-08-21"},{"lineNumber":11,"author":{"gitId":"waynetee"},"content":"","lastModifiedDate":"2021-08-21"},{"lineNumber":12,"author":{"gitId":"waynetee"},"content":"    static void show(String... lines) {","lastModifiedDate":"2021-08-21"},{"lineNumber":13,"author":{"gitId":"waynetee"},"content":"        System.out.println(\"\\t____________________________________\");","lastModifiedDate":"2021-08-21"},{"lineNumber":14,"author":{"gitId":"waynetee"},"content":"        for (String line : lines)","lastModifiedDate":"2021-08-21"},{"lineNumber":15,"author":{"gitId":"waynetee"},"content":"            System.out.println(\"\\t \" + line);","lastModifiedDate":"2021-08-21"},{"lineNumber":16,"author":{"gitId":"waynetee"},"content":"        System.out.println(\"\\t____________________________________\");","lastModifiedDate":"2021-08-21"},{"lineNumber":17,"author":{"gitId":"waynetee"},"content":"    }","lastModifiedDate":"2021-08-21"},{"lineNumber":18,"author":{"gitId":"waynetee"},"content":"}","lastModifiedDate":"2021-08-21"}],"authorContributionMap":{"waynetee":18}},{"path":"text-ui-test/input.txt","fileType":"txt","lines":[{"lineNumber":1,"author":{"gitId":"waynetee"},"content":"todo borrow book","lastModifiedDate":"2021-08-14"},{"lineNumber":2,"author":{"gitId":"waynetee"},"content":"list","lastModifiedDate":"2021-08-14"},{"lineNumber":3,"author":{"gitId":"waynetee"},"content":"deadline return book /by 20/8/2021 1500","lastModifiedDate":"2021-08-21"},{"lineNumber":4,"author":{"gitId":"waynetee"},"content":"event project meeting /at 22/8/2021 0800","lastModifiedDate":"2021-08-21"},{"lineNumber":5,"author":{"gitId":"waynetee"},"content":"list","lastModifiedDate":"2021-08-14"},{"lineNumber":6,"author":{"gitId":"waynetee"},"content":"done 1","lastModifiedDate":"2021-08-14"},{"lineNumber":7,"author":{"gitId":"waynetee"},"content":"done 3","lastModifiedDate":"2021-08-14"},{"lineNumber":8,"author":{"gitId":"waynetee"},"content":"list","lastModifiedDate":"2021-08-14"},{"lineNumber":9,"author":{"gitId":"waynetee"},"content":"blah","lastModifiedDate":"2021-08-14"},{"lineNumber":10,"author":{"gitId":"waynetee"},"content":"todo","lastModifiedDate":"2021-08-14"},{"lineNumber":11,"author":{"gitId":"waynetee"},"content":"delete 2","lastModifiedDate":"2021-08-14"},{"lineNumber":12,"author":{"gitId":"waynetee"},"content":"list","lastModifiedDate":"2021-08-14"},{"lineNumber":13,"author":{"gitId":"waynetee"},"content":"delete 3","lastModifiedDate":"2021-08-14"},{"lineNumber":14,"author":{"gitId":"waynetee"},"content":"list","lastModifiedDate":"2021-08-14"},{"lineNumber":15,"author":{"gitId":"waynetee"},"content":"bye","lastModifiedDate":"2021-08-14"}],"authorContributionMap":{"waynetee":15}},{"path":"text-ui-test/runtest.bat","fileType":"bat","lines":[{"lineNumber":1,"author":{"gitId":"-"},"content":"@ECHO OFF","lastModifiedDate":"2020-05-25"},{"lineNumber":2,"author":{"gitId":"-"},"content":"","lastModifiedDate":"2020-05-25"},{"lineNumber":3,"author":{"gitId":"-"},"content":"REM create bin directory if it doesn\u0027t exist","lastModifiedDate":"2020-05-25"},{"lineNumber":4,"author":{"gitId":"-"},"content":"if not exist ..\\bin mkdir ..\\bin","lastModifiedDate":"2020-05-25"},{"lineNumber":5,"author":{"gitId":"-"},"content":"","lastModifiedDate":"2020-05-25"},{"lineNumber":6,"author":{"gitId":"-"},"content":"REM delete output from previous run","lastModifiedDate":"2020-05-25"},{"lineNumber":7,"author":{"gitId":"-"},"content":"if exist ACTUAL.TXT del ACTUAL.TXT","lastModifiedDate":"2020-08-25"},{"lineNumber":8,"author":{"gitId":"waynetee"},"content":"if exist duke.txt del duke.txt","lastModifiedDate":"2021-08-21"},{"lineNumber":9,"author":{"gitId":"-"},"content":"","lastModifiedDate":"2020-05-25"},{"lineNumber":10,"author":{"gitId":"-"},"content":"REM compile the code into the bin folder","lastModifiedDate":"2020-05-25"},{"lineNumber":11,"author":{"gitId":"waynetee"},"content":"javac  -cp ..\\src\\main\\java -Xlint:none -d ..\\bin ..\\src\\main\\java\\duke\\*.java","lastModifiedDate":"2021-08-21"},{"lineNumber":12,"author":{"gitId":"-"},"content":"IF ERRORLEVEL 1 (","lastModifiedDate":"2020-05-25"},{"lineNumber":13,"author":{"gitId":"-"},"content":"    echo ********** BUILD FAILURE **********","lastModifiedDate":"2020-05-25"},{"lineNumber":14,"author":{"gitId":"-"},"content":"    exit /b 1","lastModifiedDate":"2020-05-25"},{"lineNumber":15,"author":{"gitId":"-"},"content":")","lastModifiedDate":"2020-05-25"},{"lineNumber":16,"author":{"gitId":"-"},"content":"REM no error here, errorlevel \u003d\u003d 0","lastModifiedDate":"2020-05-25"},{"lineNumber":17,"author":{"gitId":"-"},"content":"","lastModifiedDate":"2020-05-25"},{"lineNumber":18,"author":{"gitId":"-"},"content":"REM run the program, feed commands from input.txt file and redirect the output to the ACTUAL.TXT","lastModifiedDate":"2020-05-25"},{"lineNumber":19,"author":{"gitId":"-"},"content":"java -classpath ..\\bin Duke \u003c input.txt \u003e ACTUAL.TXT","lastModifiedDate":"2020-05-25"},{"lineNumber":20,"author":{"gitId":"-"},"content":"","lastModifiedDate":"2020-05-25"},{"lineNumber":21,"author":{"gitId":"-"},"content":"REM compare the output to the expected output","lastModifiedDate":"2020-05-25"},{"lineNumber":22,"author":{"gitId":"-"},"content":"FC ACTUAL.TXT EXPECTED.TXT","lastModifiedDate":"2020-05-25"}],"authorContributionMap":{"-":20,"waynetee":2}},{"path":"text-ui-test/runtest.sh","fileType":"sh","lines":[{"lineNumber":1,"author":{"gitId":"-"},"content":"#!/usr/bin/env bash","lastModifiedDate":"2020-05-25"},{"lineNumber":2,"author":{"gitId":"-"},"content":"","lastModifiedDate":"2020-05-25"},{"lineNumber":3,"author":{"gitId":"-"},"content":"# create bin directory if it doesn\u0027t exist","lastModifiedDate":"2020-05-25"},{"lineNumber":4,"author":{"gitId":"-"},"content":"if [ ! -d \"../bin\" ]","lastModifiedDate":"2020-05-25"},{"lineNumber":5,"author":{"gitId":"-"},"content":"then","lastModifiedDate":"2020-05-25"},{"lineNumber":6,"author":{"gitId":"-"},"content":"    mkdir ../bin","lastModifiedDate":"2020-05-25"},{"lineNumber":7,"author":{"gitId":"-"},"content":"fi","lastModifiedDate":"2020-05-25"},{"lineNumber":8,"author":{"gitId":"-"},"content":"","lastModifiedDate":"2020-05-25"},{"lineNumber":9,"author":{"gitId":"-"},"content":"# delete output from previous run","lastModifiedDate":"2020-05-25"},{"lineNumber":10,"author":{"gitId":"-"},"content":"if [ -e \"./ACTUAL.TXT\" ]","lastModifiedDate":"2020-05-25"},{"lineNumber":11,"author":{"gitId":"-"},"content":"then","lastModifiedDate":"2020-05-25"},{"lineNumber":12,"author":{"gitId":"-"},"content":"    rm ACTUAL.TXT","lastModifiedDate":"2020-05-25"},{"lineNumber":13,"author":{"gitId":"waynetee"},"content":"    rm duke.txt","lastModifiedDate":"2021-08-21"},{"lineNumber":14,"author":{"gitId":"-"},"content":"fi","lastModifiedDate":"2020-05-25"},{"lineNumber":15,"author":{"gitId":"-"},"content":"","lastModifiedDate":"2020-05-25"},{"lineNumber":16,"author":{"gitId":"waynetee"},"content":"","lastModifiedDate":"2021-08-21"},{"lineNumber":17,"author":{"gitId":"-"},"content":"# compile the code into the bin folder, terminates if error occurred","lastModifiedDate":"2020-05-25"},{"lineNumber":18,"author":{"gitId":"waynetee"},"content":"if ! javac -cp ../src/main/java -Xlint:none -d ../bin ../src/main/java/duke/*.java","lastModifiedDate":"2021-08-21"},{"lineNumber":19,"author":{"gitId":"-"},"content":"then","lastModifiedDate":"2020-05-25"},{"lineNumber":20,"author":{"gitId":"-"},"content":"    echo \"********** BUILD FAILURE **********\"","lastModifiedDate":"2020-05-25"},{"lineNumber":21,"author":{"gitId":"-"},"content":"    exit 1","lastModifiedDate":"2020-05-25"},{"lineNumber":22,"author":{"gitId":"-"},"content":"fi","lastModifiedDate":"2020-05-25"},{"lineNumber":23,"author":{"gitId":"-"},"content":"","lastModifiedDate":"2020-05-25"},{"lineNumber":24,"author":{"gitId":"-"},"content":"# run the program, feed commands from input.txt file and redirect the output to the ACTUAL.TXT","lastModifiedDate":"2020-05-25"},{"lineNumber":25,"author":{"gitId":"-"},"content":"java -classpath ../bin Duke \u003c input.txt \u003e ACTUAL.TXT","lastModifiedDate":"2020-05-25"},{"lineNumber":26,"author":{"gitId":"-"},"content":"","lastModifiedDate":"2020-05-25"},{"lineNumber":27,"author":{"gitId":"-"},"content":"# convert to UNIX format","lastModifiedDate":"2020-05-25"},{"lineNumber":28,"author":{"gitId":"-"},"content":"cp EXPECTED.TXT EXPECTED-UNIX.TXT","lastModifiedDate":"2020-05-25"},{"lineNumber":29,"author":{"gitId":"-"},"content":"dos2unix ACTUAL.TXT EXPECTED-UNIX.TXT","lastModifiedDate":"2020-05-25"},{"lineNumber":30,"author":{"gitId":"-"},"content":"","lastModifiedDate":"2020-05-25"},{"lineNumber":31,"author":{"gitId":"-"},"content":"# compare the output to the expected output","lastModifiedDate":"2020-05-25"},{"lineNumber":32,"author":{"gitId":"-"},"content":"diff ACTUAL.TXT EXPECTED-UNIX.TXT","lastModifiedDate":"2020-05-25"},{"lineNumber":33,"author":{"gitId":"-"},"content":"if [ $? -eq 0 ]","lastModifiedDate":"2020-05-25"},{"lineNumber":34,"author":{"gitId":"-"},"content":"then","lastModifiedDate":"2020-05-25"},{"lineNumber":35,"author":{"gitId":"-"},"content":"    echo \"Test result: PASSED\"","lastModifiedDate":"2020-05-25"},{"lineNumber":36,"author":{"gitId":"-"},"content":"    exit 0","lastModifiedDate":"2020-05-25"},{"lineNumber":37,"author":{"gitId":"-"},"content":"else","lastModifiedDate":"2020-05-25"},{"lineNumber":38,"author":{"gitId":"-"},"content":"    echo \"Test result: FAILED\"","lastModifiedDate":"2020-05-25"},{"lineNumber":39,"author":{"gitId":"-"},"content":"    exit 1","lastModifiedDate":"2020-05-25"},{"lineNumber":40,"author":{"gitId":"-"},"content":"fi","lastModifiedDate":"2020-05-25"}],"authorContributionMap":{"-":37,"waynetee":3}}]
