[{"path":"src/main/data/tasks.txt","fileType":"txt","lines":[{"lineNumber":1,"author":{"gitId":"wanninglim"},"content":"T - 0 - read book","lastModifiedDate":"2021-08-25"},{"lineNumber":2,"author":{"gitId":"wanninglim"},"content":"D - 1 - return book - Jun 6 2020","lastModifiedDate":"2021-08-25"},{"lineNumber":3,"author":{"gitId":"wanninglim"},"content":"E - 1 - project meeting - Aug 6 2020","lastModifiedDate":"2021-08-25"},{"lineNumber":4,"author":{"gitId":"wanninglim"},"content":"T - 0 - soccer training","lastModifiedDate":"2021-08-25"}],"authorContributionMap":{"wanninglim":4}},{"path":"src/main/java/ponyo/Ponyo.java","fileType":"java","lines":[{"lineNumber":1,"author":{"gitId":"wanninglim"},"content":"package ponyo;","lastModifiedDate":"2021-08-25"},{"lineNumber":2,"author":{"gitId":"wanninglim"},"content":"","lastModifiedDate":"2021-08-25"},{"lineNumber":3,"author":{"gitId":"wanninglim"},"content":"import ponyo.data.task.TaskList;","lastModifiedDate":"2021-08-25"},{"lineNumber":4,"author":{"gitId":"wanninglim"},"content":"import ponyo.commands.Command;","lastModifiedDate":"2021-08-25"},{"lineNumber":5,"author":{"gitId":"wanninglim"},"content":"import ponyo.ui.Ui;","lastModifiedDate":"2021-08-25"},{"lineNumber":6,"author":{"gitId":"wanninglim"},"content":"import ponyo.storage.Storage;","lastModifiedDate":"2021-08-25"},{"lineNumber":7,"author":{"gitId":"wanninglim"},"content":"import ponyo.parser.Parser;","lastModifiedDate":"2021-08-25"},{"lineNumber":8,"author":{"gitId":"wanninglim"},"content":"import ponyo.data.exceptions.PonyoException;","lastModifiedDate":"2021-08-25"},{"lineNumber":9,"author":{"gitId":"wanninglim"},"content":"","lastModifiedDate":"2021-08-25"},{"lineNumber":10,"author":{"gitId":"wanninglim"},"content":"public class Ponyo {","lastModifiedDate":"2021-08-25"},{"lineNumber":11,"author":{"gitId":"wanninglim"},"content":"    // CONSTANTS","lastModifiedDate":"2021-08-24"},{"lineNumber":12,"author":{"gitId":"wanninglim"},"content":"    private static final String PATH \u003d \"src/main/data\";","lastModifiedDate":"2021-08-24"},{"lineNumber":13,"author":{"gitId":"wanninglim"},"content":"    private static final String FILENAME \u003d \"tasks.txt\";","lastModifiedDate":"2021-08-25"},{"lineNumber":14,"author":{"gitId":"wanninglim"},"content":"","lastModifiedDate":"2021-08-24"},{"lineNumber":15,"author":{"gitId":"wanninglim"},"content":"    private final Storage storage;","lastModifiedDate":"2021-08-25"},{"lineNumber":16,"author":{"gitId":"wanninglim"},"content":"    private TaskList tasks;","lastModifiedDate":"2021-08-25"},{"lineNumber":17,"author":{"gitId":"wanninglim"},"content":"    private final Ui ui;","lastModifiedDate":"2021-08-25"},{"lineNumber":18,"author":{"gitId":"wanninglim"},"content":"","lastModifiedDate":"2021-08-18"},{"lineNumber":19,"author":{"gitId":"wanninglim"},"content":"    public Ponyo(String filePath) {","lastModifiedDate":"2021-08-25"},{"lineNumber":20,"author":{"gitId":"wanninglim"},"content":"        ui \u003d new Ui();","lastModifiedDate":"2021-08-25"},{"lineNumber":21,"author":{"gitId":"wanninglim"},"content":"        storage \u003d new Storage(filePath);","lastModifiedDate":"2021-08-25"},{"lineNumber":22,"author":{"gitId":"wanninglim"},"content":"        try {","lastModifiedDate":"2021-08-19"},{"lineNumber":23,"author":{"gitId":"wanninglim"},"content":"            tasks \u003d new TaskList(storage.load());","lastModifiedDate":"2021-08-25"},{"lineNumber":24,"author":{"gitId":"wanninglim"},"content":"        } catch (PonyoException e) {","lastModifiedDate":"2021-08-25"},{"lineNumber":25,"author":{"gitId":"wanninglim"},"content":"            ui.showLoadingError();","lastModifiedDate":"2021-08-25"},{"lineNumber":26,"author":{"gitId":"wanninglim"},"content":"            tasks \u003d new TaskList();","lastModifiedDate":"2021-08-25"},{"lineNumber":27,"author":{"gitId":"-"},"content":"        }","lastModifiedDate":"2019-07-29"},{"lineNumber":28,"author":{"gitId":"wanninglim"},"content":"    }","lastModifiedDate":"2021-08-19"},{"lineNumber":29,"author":{"gitId":"wanninglim"},"content":"","lastModifiedDate":"2021-08-24"},{"lineNumber":30,"author":{"gitId":"wanninglim"},"content":"    public void run() {","lastModifiedDate":"2021-08-25"},{"lineNumber":31,"author":{"gitId":"wanninglim"},"content":"        ui.showWelcomeMessage();","lastModifiedDate":"2021-08-25"},{"lineNumber":32,"author":{"gitId":"wanninglim"},"content":"        boolean isExit \u003d false;","lastModifiedDate":"2021-08-25"},{"lineNumber":33,"author":{"gitId":"wanninglim"},"content":"","lastModifiedDate":"2021-08-24"},{"lineNumber":34,"author":{"gitId":"wanninglim"},"content":"        while (!isExit) {","lastModifiedDate":"2021-08-25"},{"lineNumber":35,"author":{"gitId":"wanninglim"},"content":"            try {","lastModifiedDate":"2021-08-24"},{"lineNumber":36,"author":{"gitId":"wanninglim"},"content":"                String fullCommand \u003d ui.readCommand();","lastModifiedDate":"2021-08-25"},{"lineNumber":37,"author":{"gitId":"wanninglim"},"content":"                ui.showLine(); // show the divider line (\"_______\")","lastModifiedDate":"2021-08-25"},{"lineNumber":38,"author":{"gitId":"wanninglim"},"content":"                Command c \u003d Parser.parse(fullCommand);","lastModifiedDate":"2021-08-25"},{"lineNumber":39,"author":{"gitId":"wanninglim"},"content":"                c.execute(tasks, ui, storage);","lastModifiedDate":"2021-08-25"},{"lineNumber":40,"author":{"gitId":"wanninglim"},"content":"                isExit \u003d c.isExit();","lastModifiedDate":"2021-08-25"},{"lineNumber":41,"author":{"gitId":"wanninglim"},"content":"            } catch (PonyoException e) {","lastModifiedDate":"2021-08-25"},{"lineNumber":42,"author":{"gitId":"wanninglim"},"content":"                ui.showError(e.getMessage());","lastModifiedDate":"2021-08-25"},{"lineNumber":43,"author":{"gitId":"wanninglim"},"content":"            } finally {","lastModifiedDate":"2021-08-25"},{"lineNumber":44,"author":{"gitId":"wanninglim"},"content":"                ui.showLine();","lastModifiedDate":"2021-08-25"},{"lineNumber":45,"author":{"gitId":"wanninglim"},"content":"            }","lastModifiedDate":"2021-08-24"},{"lineNumber":46,"author":{"gitId":"wanninglim"},"content":"        }","lastModifiedDate":"2021-08-24"},{"lineNumber":47,"author":{"gitId":"wanninglim"},"content":"    }","lastModifiedDate":"2021-08-24"},{"lineNumber":48,"author":{"gitId":"wanninglim"},"content":"","lastModifiedDate":"2021-08-24"},{"lineNumber":49,"author":{"gitId":"wanninglim"},"content":"    public static void main(String[] args) {","lastModifiedDate":"2021-08-25"},{"lineNumber":50,"author":{"gitId":"wanninglim"},"content":"        new Ponyo(PATH + \"/\" + FILENAME).run();","lastModifiedDate":"2021-08-25"},{"lineNumber":51,"author":{"gitId":"wanninglim"},"content":"    }","lastModifiedDate":"2021-08-24"},{"lineNumber":52,"author":{"gitId":"-"},"content":"}","lastModifiedDate":"2019-07-29"}],"authorContributionMap":{"wanninglim":50,"-":2}},{"path":"src/main/java/ponyo/commands/AddCommand.java","fileType":"java","lines":[{"lineNumber":1,"author":{"gitId":"wanninglim"},"content":"package ponyo.commands;","lastModifiedDate":"2021-08-25"},{"lineNumber":2,"author":{"gitId":"wanninglim"},"content":"","lastModifiedDate":"2021-08-25"},{"lineNumber":3,"author":{"gitId":"wanninglim"},"content":"import java.time.LocalDate;","lastModifiedDate":"2021-08-25"},{"lineNumber":4,"author":{"gitId":"wanninglim"},"content":"import java.time.format.DateTimeFormatter;","lastModifiedDate":"2021-08-25"},{"lineNumber":5,"author":{"gitId":"wanninglim"},"content":"import java.time.format.DateTimeParseException;","lastModifiedDate":"2021-08-25"},{"lineNumber":6,"author":{"gitId":"wanninglim"},"content":"","lastModifiedDate":"2021-08-25"},{"lineNumber":7,"author":{"gitId":"wanninglim"},"content":"import ponyo.data.task.Task;","lastModifiedDate":"2021-08-25"},{"lineNumber":8,"author":{"gitId":"wanninglim"},"content":"import ponyo.data.task.TaskList;","lastModifiedDate":"2021-08-25"},{"lineNumber":9,"author":{"gitId":"wanninglim"},"content":"import ponyo.data.task.Todo;","lastModifiedDate":"2021-08-25"},{"lineNumber":10,"author":{"gitId":"wanninglim"},"content":"import ponyo.data.task.Deadline;","lastModifiedDate":"2021-08-25"},{"lineNumber":11,"author":{"gitId":"wanninglim"},"content":"import ponyo.data.task.Event;","lastModifiedDate":"2021-08-25"},{"lineNumber":12,"author":{"gitId":"wanninglim"},"content":"import ponyo.ui.Ui;","lastModifiedDate":"2021-08-25"},{"lineNumber":13,"author":{"gitId":"wanninglim"},"content":"import ponyo.storage.Storage;","lastModifiedDate":"2021-08-25"},{"lineNumber":14,"author":{"gitId":"wanninglim"},"content":"","lastModifiedDate":"2021-08-25"},{"lineNumber":15,"author":{"gitId":"wanninglim"},"content":"public class AddCommand extends Command {","lastModifiedDate":"2021-08-25"},{"lineNumber":16,"author":{"gitId":"wanninglim"},"content":"    private final String[] taskToAdd;","lastModifiedDate":"2021-08-25"},{"lineNumber":17,"author":{"gitId":"wanninglim"},"content":"","lastModifiedDate":"2021-08-25"},{"lineNumber":18,"author":{"gitId":"wanninglim"},"content":"    public AddCommand(String[] taskToAdd) {","lastModifiedDate":"2021-08-25"},{"lineNumber":19,"author":{"gitId":"wanninglim"},"content":"        this.taskToAdd \u003d taskToAdd;","lastModifiedDate":"2021-08-25"},{"lineNumber":20,"author":{"gitId":"wanninglim"},"content":"    }","lastModifiedDate":"2021-08-25"},{"lineNumber":21,"author":{"gitId":"wanninglim"},"content":"","lastModifiedDate":"2021-08-25"},{"lineNumber":22,"author":{"gitId":"wanninglim"},"content":"    @Override","lastModifiedDate":"2021-08-25"},{"lineNumber":23,"author":{"gitId":"wanninglim"},"content":"    public void execute(TaskList tasks, Ui ui, Storage storage) {","lastModifiedDate":"2021-08-25"},{"lineNumber":24,"author":{"gitId":"wanninglim"},"content":"        switch (taskToAdd[0]) {","lastModifiedDate":"2021-08-25"},{"lineNumber":25,"author":{"gitId":"wanninglim"},"content":"            case \"todo\":","lastModifiedDate":"2021-08-25"},{"lineNumber":26,"author":{"gitId":"wanninglim"},"content":"                try {","lastModifiedDate":"2021-08-25"},{"lineNumber":27,"author":{"gitId":"wanninglim"},"content":"                    Task t \u003d new Todo(taskToAdd[1]);","lastModifiedDate":"2021-08-25"},{"lineNumber":28,"author":{"gitId":"wanninglim"},"content":"                    tasks.add(t);","lastModifiedDate":"2021-08-25"},{"lineNumber":29,"author":{"gitId":"wanninglim"},"content":"                    storage.fileLineToWrite(t);","lastModifiedDate":"2021-08-25"},{"lineNumber":30,"author":{"gitId":"wanninglim"},"content":"                    showTask(t, tasks.size(), ui);","lastModifiedDate":"2021-08-25"},{"lineNumber":31,"author":{"gitId":"wanninglim"},"content":"                } catch (ArrayIndexOutOfBoundsException e){","lastModifiedDate":"2021-08-25"},{"lineNumber":32,"author":{"gitId":"wanninglim"},"content":"                    ui.show(\"\\t☹ OOPS!!! The description of a todo cannot be empty.\");","lastModifiedDate":"2021-08-25"},{"lineNumber":33,"author":{"gitId":"wanninglim"},"content":"                }","lastModifiedDate":"2021-08-25"},{"lineNumber":34,"author":{"gitId":"wanninglim"},"content":"                break;","lastModifiedDate":"2021-08-25"},{"lineNumber":35,"author":{"gitId":"wanninglim"},"content":"            case \"deadline\":","lastModifiedDate":"2021-08-25"},{"lineNumber":36,"author":{"gitId":"wanninglim"},"content":"                try {","lastModifiedDate":"2021-08-25"},{"lineNumber":37,"author":{"gitId":"wanninglim"},"content":"                    int slashIndex \u003d taskToAdd[1].indexOf(\"/\");","lastModifiedDate":"2021-08-25"},{"lineNumber":38,"author":{"gitId":"wanninglim"},"content":"                    Task t \u003d new Deadline(taskToAdd[1].substring(0, slashIndex), dateFormatter(taskToAdd[1], slashIndex));","lastModifiedDate":"2021-08-25"},{"lineNumber":39,"author":{"gitId":"wanninglim"},"content":"                    tasks.add(t);","lastModifiedDate":"2021-08-25"},{"lineNumber":40,"author":{"gitId":"wanninglim"},"content":"                    storage.fileLineToWrite(t);","lastModifiedDate":"2021-08-25"},{"lineNumber":41,"author":{"gitId":"wanninglim"},"content":"                    showTask(t, tasks.size(), ui);","lastModifiedDate":"2021-08-25"},{"lineNumber":42,"author":{"gitId":"wanninglim"},"content":"                } catch (ArrayIndexOutOfBoundsException e){","lastModifiedDate":"2021-08-25"},{"lineNumber":43,"author":{"gitId":"wanninglim"},"content":"                    ui.show(\"\\t☹ OOPS!!! The description of a deadline cannot be empty.\");","lastModifiedDate":"2021-08-25"},{"lineNumber":44,"author":{"gitId":"wanninglim"},"content":"                } catch (DateTimeParseException e) {","lastModifiedDate":"2021-08-25"},{"lineNumber":45,"author":{"gitId":"wanninglim"},"content":"                    ui.show(\"\\t☹ OOPS!!! Please use the date format: yyyy-mm-dd.\");","lastModifiedDate":"2021-08-25"},{"lineNumber":46,"author":{"gitId":"wanninglim"},"content":"                }","lastModifiedDate":"2021-08-25"},{"lineNumber":47,"author":{"gitId":"wanninglim"},"content":"                break;","lastModifiedDate":"2021-08-25"},{"lineNumber":48,"author":{"gitId":"wanninglim"},"content":"            case \"event\":","lastModifiedDate":"2021-08-25"},{"lineNumber":49,"author":{"gitId":"wanninglim"},"content":"                try {","lastModifiedDate":"2021-08-25"},{"lineNumber":50,"author":{"gitId":"wanninglim"},"content":"                    int slashIndex \u003d taskToAdd[1].indexOf(\"/\");","lastModifiedDate":"2021-08-25"},{"lineNumber":51,"author":{"gitId":"wanninglim"},"content":"                    Task t \u003d new Event(taskToAdd[1].substring(0, slashIndex), dateFormatter(taskToAdd[1], slashIndex));","lastModifiedDate":"2021-08-25"},{"lineNumber":52,"author":{"gitId":"wanninglim"},"content":"                    tasks.add(t);","lastModifiedDate":"2021-08-25"},{"lineNumber":53,"author":{"gitId":"wanninglim"},"content":"                    storage.fileLineToWrite(t);","lastModifiedDate":"2021-08-25"},{"lineNumber":54,"author":{"gitId":"wanninglim"},"content":"                    showTask(t, tasks.size(), ui);","lastModifiedDate":"2021-08-25"},{"lineNumber":55,"author":{"gitId":"wanninglim"},"content":"                } catch (ArrayIndexOutOfBoundsException e){","lastModifiedDate":"2021-08-25"},{"lineNumber":56,"author":{"gitId":"wanninglim"},"content":"                    ui.show(\"\\t☹ OOPS!!! The description of an event cannot be empty.\");","lastModifiedDate":"2021-08-25"},{"lineNumber":57,"author":{"gitId":"wanninglim"},"content":"                } catch (DateTimeParseException e) {","lastModifiedDate":"2021-08-25"},{"lineNumber":58,"author":{"gitId":"wanninglim"},"content":"                    ui.show(\"\\t☹ OOPS!!! Please use the date format: yyyy-mm-dd.\");","lastModifiedDate":"2021-08-25"},{"lineNumber":59,"author":{"gitId":"wanninglim"},"content":"                }","lastModifiedDate":"2021-08-25"},{"lineNumber":60,"author":{"gitId":"wanninglim"},"content":"                break;","lastModifiedDate":"2021-08-25"},{"lineNumber":61,"author":{"gitId":"wanninglim"},"content":"        }","lastModifiedDate":"2021-08-25"},{"lineNumber":62,"author":{"gitId":"wanninglim"},"content":"    }","lastModifiedDate":"2021-08-25"},{"lineNumber":63,"author":{"gitId":"wanninglim"},"content":"","lastModifiedDate":"2021-08-25"},{"lineNumber":64,"author":{"gitId":"wanninglim"},"content":"    public static void showTask(Task task, int size, Ui ui) {","lastModifiedDate":"2021-08-25"},{"lineNumber":65,"author":{"gitId":"wanninglim"},"content":"        ui.show(\"\\tGot it. I\u0027ve added this task:\",","lastModifiedDate":"2021-08-25"},{"lineNumber":66,"author":{"gitId":"wanninglim"},"content":"                \"\\t\\t\" + task,","lastModifiedDate":"2021-08-25"},{"lineNumber":67,"author":{"gitId":"wanninglim"},"content":"                \"\\tNow you have \" + size + \" tasks in the list.\");","lastModifiedDate":"2021-08-25"},{"lineNumber":68,"author":{"gitId":"wanninglim"},"content":"    }","lastModifiedDate":"2021-08-25"},{"lineNumber":69,"author":{"gitId":"wanninglim"},"content":"","lastModifiedDate":"2021-08-25"},{"lineNumber":70,"author":{"gitId":"wanninglim"},"content":"    public String dateFormatter(String inputDate, int slashIndex) throws DateTimeParseException {","lastModifiedDate":"2021-08-25"},{"lineNumber":71,"author":{"gitId":"wanninglim"},"content":"        LocalDate date \u003d LocalDate.parse(inputDate.substring(slashIndex + 4));","lastModifiedDate":"2021-08-25"},{"lineNumber":72,"author":{"gitId":"wanninglim"},"content":"        return date.format(DateTimeFormatter.ofPattern(\"MMM d yyyy\"));","lastModifiedDate":"2021-08-25"},{"lineNumber":73,"author":{"gitId":"wanninglim"},"content":"    }","lastModifiedDate":"2021-08-25"},{"lineNumber":74,"author":{"gitId":"wanninglim"},"content":"","lastModifiedDate":"2021-08-25"},{"lineNumber":75,"author":{"gitId":"wanninglim"},"content":"    @Override","lastModifiedDate":"2021-08-25"},{"lineNumber":76,"author":{"gitId":"wanninglim"},"content":"    public boolean isExit() {","lastModifiedDate":"2021-08-25"},{"lineNumber":77,"author":{"gitId":"wanninglim"},"content":"        return false;","lastModifiedDate":"2021-08-25"},{"lineNumber":78,"author":{"gitId":"wanninglim"},"content":"    }","lastModifiedDate":"2021-08-25"},{"lineNumber":79,"author":{"gitId":"wanninglim"},"content":"}","lastModifiedDate":"2021-08-25"}],"authorContributionMap":{"wanninglim":79}},{"path":"src/main/java/ponyo/commands/Command.java","fileType":"java","lines":[{"lineNumber":1,"author":{"gitId":"wanninglim"},"content":"package ponyo.commands;","lastModifiedDate":"2021-08-25"},{"lineNumber":2,"author":{"gitId":"wanninglim"},"content":"","lastModifiedDate":"2021-08-25"},{"lineNumber":3,"author":{"gitId":"wanninglim"},"content":"import ponyo.data.task.TaskList;","lastModifiedDate":"2021-08-25"},{"lineNumber":4,"author":{"gitId":"wanninglim"},"content":"import ponyo.ui.Ui;","lastModifiedDate":"2021-08-25"},{"lineNumber":5,"author":{"gitId":"wanninglim"},"content":"import ponyo.storage.Storage;","lastModifiedDate":"2021-08-25"},{"lineNumber":6,"author":{"gitId":"wanninglim"},"content":"","lastModifiedDate":"2021-08-25"},{"lineNumber":7,"author":{"gitId":"wanninglim"},"content":"public abstract class Command {","lastModifiedDate":"2021-08-25"},{"lineNumber":8,"author":{"gitId":"wanninglim"},"content":"    public abstract void execute(TaskList tasks, Ui ui, Storage storage);","lastModifiedDate":"2021-08-25"},{"lineNumber":9,"author":{"gitId":"wanninglim"},"content":"    public abstract boolean isExit();","lastModifiedDate":"2021-08-25"},{"lineNumber":10,"author":{"gitId":"wanninglim"},"content":"}","lastModifiedDate":"2021-08-25"}],"authorContributionMap":{"wanninglim":10}},{"path":"src/main/java/ponyo/commands/DeleteCommand.java","fileType":"java","lines":[{"lineNumber":1,"author":{"gitId":"wanninglim"},"content":"package ponyo.commands;","lastModifiedDate":"2021-08-25"},{"lineNumber":2,"author":{"gitId":"wanninglim"},"content":"","lastModifiedDate":"2021-08-25"},{"lineNumber":3,"author":{"gitId":"wanninglim"},"content":"import ponyo.data.task.TaskList;","lastModifiedDate":"2021-08-25"},{"lineNumber":4,"author":{"gitId":"wanninglim"},"content":"import ponyo.ui.Ui;","lastModifiedDate":"2021-08-25"},{"lineNumber":5,"author":{"gitId":"wanninglim"},"content":"import ponyo.storage.Storage;","lastModifiedDate":"2021-08-25"},{"lineNumber":6,"author":{"gitId":"wanninglim"},"content":"","lastModifiedDate":"2021-08-25"},{"lineNumber":7,"author":{"gitId":"wanninglim"},"content":"public class DeleteCommand extends Command {","lastModifiedDate":"2021-08-25"},{"lineNumber":8,"author":{"gitId":"wanninglim"},"content":"    private final int taskToDelete;","lastModifiedDate":"2021-08-25"},{"lineNumber":9,"author":{"gitId":"wanninglim"},"content":"","lastModifiedDate":"2021-08-25"},{"lineNumber":10,"author":{"gitId":"wanninglim"},"content":"    public DeleteCommand(int taskToDelete) {","lastModifiedDate":"2021-08-25"},{"lineNumber":11,"author":{"gitId":"wanninglim"},"content":"        this.taskToDelete \u003d taskToDelete;","lastModifiedDate":"2021-08-25"},{"lineNumber":12,"author":{"gitId":"wanninglim"},"content":"    }","lastModifiedDate":"2021-08-25"},{"lineNumber":13,"author":{"gitId":"wanninglim"},"content":"","lastModifiedDate":"2021-08-25"},{"lineNumber":14,"author":{"gitId":"wanninglim"},"content":"    @Override","lastModifiedDate":"2021-08-25"},{"lineNumber":15,"author":{"gitId":"wanninglim"},"content":"    public void execute(TaskList tasks, Ui ui, Storage storage) {","lastModifiedDate":"2021-08-25"},{"lineNumber":16,"author":{"gitId":"wanninglim"},"content":"        tasks.remove(taskToDelete);","lastModifiedDate":"2021-08-25"},{"lineNumber":17,"author":{"gitId":"wanninglim"},"content":"        storage.getFullContents(tasks);","lastModifiedDate":"2021-08-25"},{"lineNumber":18,"author":{"gitId":"wanninglim"},"content":"        ui.show(\"\\tNoted. I\u0027ve removed this task: \\n\\t\\t\" +","lastModifiedDate":"2021-08-25"},{"lineNumber":19,"author":{"gitId":"wanninglim"},"content":"                tasks.retrieveTask(taskToDelete - 1),","lastModifiedDate":"2021-08-25"},{"lineNumber":20,"author":{"gitId":"wanninglim"},"content":"                \"\\tNow you have \" + tasks.size() + \" tasks in the list.\");","lastModifiedDate":"2021-08-25"},{"lineNumber":21,"author":{"gitId":"wanninglim"},"content":"    }","lastModifiedDate":"2021-08-25"},{"lineNumber":22,"author":{"gitId":"wanninglim"},"content":"","lastModifiedDate":"2021-08-25"},{"lineNumber":23,"author":{"gitId":"wanninglim"},"content":"    @Override","lastModifiedDate":"2021-08-25"},{"lineNumber":24,"author":{"gitId":"wanninglim"},"content":"    public boolean isExit() {","lastModifiedDate":"2021-08-25"},{"lineNumber":25,"author":{"gitId":"wanninglim"},"content":"        return false;","lastModifiedDate":"2021-08-25"},{"lineNumber":26,"author":{"gitId":"wanninglim"},"content":"    }","lastModifiedDate":"2021-08-25"},{"lineNumber":27,"author":{"gitId":"wanninglim"},"content":"}","lastModifiedDate":"2021-08-25"}],"authorContributionMap":{"wanninglim":27}},{"path":"src/main/java/ponyo/commands/DoneCommand.java","fileType":"java","lines":[{"lineNumber":1,"author":{"gitId":"wanninglim"},"content":"package ponyo.commands;","lastModifiedDate":"2021-08-25"},{"lineNumber":2,"author":{"gitId":"wanninglim"},"content":"","lastModifiedDate":"2021-08-25"},{"lineNumber":3,"author":{"gitId":"wanninglim"},"content":"import ponyo.data.task.TaskList;","lastModifiedDate":"2021-08-25"},{"lineNumber":4,"author":{"gitId":"wanninglim"},"content":"import ponyo.ui.Ui;","lastModifiedDate":"2021-08-25"},{"lineNumber":5,"author":{"gitId":"wanninglim"},"content":"import ponyo.storage.Storage;","lastModifiedDate":"2021-08-25"},{"lineNumber":6,"author":{"gitId":"wanninglim"},"content":"","lastModifiedDate":"2021-08-25"},{"lineNumber":7,"author":{"gitId":"wanninglim"},"content":"public class DoneCommand extends Command {","lastModifiedDate":"2021-08-25"},{"lineNumber":8,"author":{"gitId":"wanninglim"},"content":"    private final int taskToMarkDone;","lastModifiedDate":"2021-08-25"},{"lineNumber":9,"author":{"gitId":"wanninglim"},"content":"","lastModifiedDate":"2021-08-25"},{"lineNumber":10,"author":{"gitId":"wanninglim"},"content":"    public DoneCommand(int tasktoMarkDone) {","lastModifiedDate":"2021-08-25"},{"lineNumber":11,"author":{"gitId":"wanninglim"},"content":"        this.taskToMarkDone \u003d tasktoMarkDone;","lastModifiedDate":"2021-08-25"},{"lineNumber":12,"author":{"gitId":"wanninglim"},"content":"    }","lastModifiedDate":"2021-08-25"},{"lineNumber":13,"author":{"gitId":"wanninglim"},"content":"","lastModifiedDate":"2021-08-25"},{"lineNumber":14,"author":{"gitId":"wanninglim"},"content":"    @Override","lastModifiedDate":"2021-08-25"},{"lineNumber":15,"author":{"gitId":"wanninglim"},"content":"    public void execute(TaskList tasks, Ui ui, Storage storage) {","lastModifiedDate":"2021-08-25"},{"lineNumber":16,"author":{"gitId":"wanninglim"},"content":"        tasks.retrieveTask(taskToMarkDone).markAsDone();","lastModifiedDate":"2021-08-25"},{"lineNumber":17,"author":{"gitId":"wanninglim"},"content":"        storage.getFullContents(tasks);","lastModifiedDate":"2021-08-25"},{"lineNumber":18,"author":{"gitId":"wanninglim"},"content":"        ui.show(\"\\tNice! I\u0027ve marked this task as done: \\n\\t\\t\" + tasks.retrieveTask(taskToMarkDone));","lastModifiedDate":"2021-08-25"},{"lineNumber":19,"author":{"gitId":"wanninglim"},"content":"    }","lastModifiedDate":"2021-08-25"},{"lineNumber":20,"author":{"gitId":"wanninglim"},"content":"","lastModifiedDate":"2021-08-25"},{"lineNumber":21,"author":{"gitId":"wanninglim"},"content":"    @Override","lastModifiedDate":"2021-08-25"},{"lineNumber":22,"author":{"gitId":"wanninglim"},"content":"    public boolean isExit() {","lastModifiedDate":"2021-08-25"},{"lineNumber":23,"author":{"gitId":"wanninglim"},"content":"        return false;","lastModifiedDate":"2021-08-25"},{"lineNumber":24,"author":{"gitId":"wanninglim"},"content":"    }","lastModifiedDate":"2021-08-25"},{"lineNumber":25,"author":{"gitId":"wanninglim"},"content":"}","lastModifiedDate":"2021-08-25"}],"authorContributionMap":{"wanninglim":25}},{"path":"src/main/java/ponyo/commands/ExitCommand.java","fileType":"java","lines":[{"lineNumber":1,"author":{"gitId":"wanninglim"},"content":"package ponyo.commands;","lastModifiedDate":"2021-08-25"},{"lineNumber":2,"author":{"gitId":"wanninglim"},"content":"","lastModifiedDate":"2021-08-25"},{"lineNumber":3,"author":{"gitId":"wanninglim"},"content":"import ponyo.data.task.TaskList;","lastModifiedDate":"2021-08-25"},{"lineNumber":4,"author":{"gitId":"wanninglim"},"content":"import ponyo.ui.Ui;","lastModifiedDate":"2021-08-25"},{"lineNumber":5,"author":{"gitId":"wanninglim"},"content":"import ponyo.storage.Storage;","lastModifiedDate":"2021-08-25"},{"lineNumber":6,"author":{"gitId":"wanninglim"},"content":"","lastModifiedDate":"2021-08-25"},{"lineNumber":7,"author":{"gitId":"wanninglim"},"content":"public class ExitCommand extends Command {","lastModifiedDate":"2021-08-25"},{"lineNumber":8,"author":{"gitId":"wanninglim"},"content":"    private static final String MESSAGE_BYE \u003d \"\\tBye. Hope to see you again soon!\";","lastModifiedDate":"2021-08-25"},{"lineNumber":9,"author":{"gitId":"wanninglim"},"content":"","lastModifiedDate":"2021-08-25"},{"lineNumber":10,"author":{"gitId":"wanninglim"},"content":"    @Override","lastModifiedDate":"2021-08-25"},{"lineNumber":11,"author":{"gitId":"wanninglim"},"content":"    public void execute(TaskList tasks, Ui ui, Storage storage) {","lastModifiedDate":"2021-08-25"},{"lineNumber":12,"author":{"gitId":"wanninglim"},"content":"        ui.show(MESSAGE_BYE);","lastModifiedDate":"2021-08-25"},{"lineNumber":13,"author":{"gitId":"wanninglim"},"content":"    }","lastModifiedDate":"2021-08-25"},{"lineNumber":14,"author":{"gitId":"wanninglim"},"content":"","lastModifiedDate":"2021-08-25"},{"lineNumber":15,"author":{"gitId":"wanninglim"},"content":"    @Override","lastModifiedDate":"2021-08-25"},{"lineNumber":16,"author":{"gitId":"wanninglim"},"content":"    public boolean isExit() {","lastModifiedDate":"2021-08-25"},{"lineNumber":17,"author":{"gitId":"wanninglim"},"content":"        return true;","lastModifiedDate":"2021-08-25"},{"lineNumber":18,"author":{"gitId":"wanninglim"},"content":"    }","lastModifiedDate":"2021-08-25"},{"lineNumber":19,"author":{"gitId":"wanninglim"},"content":"}","lastModifiedDate":"2021-08-25"}],"authorContributionMap":{"wanninglim":19}},{"path":"src/main/java/ponyo/commands/ListCommand.java","fileType":"java","lines":[{"lineNumber":1,"author":{"gitId":"wanninglim"},"content":"package ponyo.commands;","lastModifiedDate":"2021-08-25"},{"lineNumber":2,"author":{"gitId":"wanninglim"},"content":"","lastModifiedDate":"2021-08-25"},{"lineNumber":3,"author":{"gitId":"wanninglim"},"content":"import ponyo.data.task.TaskList;","lastModifiedDate":"2021-08-25"},{"lineNumber":4,"author":{"gitId":"wanninglim"},"content":"import ponyo.ui.Ui;","lastModifiedDate":"2021-08-25"},{"lineNumber":5,"author":{"gitId":"wanninglim"},"content":"import ponyo.storage.Storage;","lastModifiedDate":"2021-08-25"},{"lineNumber":6,"author":{"gitId":"wanninglim"},"content":"","lastModifiedDate":"2021-08-25"},{"lineNumber":7,"author":{"gitId":"wanninglim"},"content":"public class ListCommand extends Command {","lastModifiedDate":"2021-08-25"},{"lineNumber":8,"author":{"gitId":"wanninglim"},"content":"    @Override","lastModifiedDate":"2021-08-25"},{"lineNumber":9,"author":{"gitId":"wanninglim"},"content":"    public void execute(TaskList tasks, Ui ui, Storage storage) {","lastModifiedDate":"2021-08-25"},{"lineNumber":10,"author":{"gitId":"wanninglim"},"content":"        for (int i \u003d 1; i \u003c\u003d tasks.size(); i++) {","lastModifiedDate":"2021-08-25"},{"lineNumber":11,"author":{"gitId":"wanninglim"},"content":"            ui.show(\"\\t\" + i + \".\" + tasks.retrieveTask(i));","lastModifiedDate":"2021-08-25"},{"lineNumber":12,"author":{"gitId":"wanninglim"},"content":"        }","lastModifiedDate":"2021-08-25"},{"lineNumber":13,"author":{"gitId":"wanninglim"},"content":"    }","lastModifiedDate":"2021-08-25"},{"lineNumber":14,"author":{"gitId":"wanninglim"},"content":"","lastModifiedDate":"2021-08-25"},{"lineNumber":15,"author":{"gitId":"wanninglim"},"content":"    @Override","lastModifiedDate":"2021-08-25"},{"lineNumber":16,"author":{"gitId":"wanninglim"},"content":"    public boolean isExit() {","lastModifiedDate":"2021-08-25"},{"lineNumber":17,"author":{"gitId":"wanninglim"},"content":"        return false;","lastModifiedDate":"2021-08-25"},{"lineNumber":18,"author":{"gitId":"wanninglim"},"content":"    }","lastModifiedDate":"2021-08-25"},{"lineNumber":19,"author":{"gitId":"wanninglim"},"content":"}","lastModifiedDate":"2021-08-25"}],"authorContributionMap":{"wanninglim":19}},{"path":"src/main/java/ponyo/data/exceptions/PonyoException.java","fileType":"java","lines":[{"lineNumber":1,"author":{"gitId":"wanninglim"},"content":"package ponyo.data.exceptions;","lastModifiedDate":"2021-08-25"},{"lineNumber":2,"author":{"gitId":"wanninglim"},"content":"","lastModifiedDate":"2021-08-25"},{"lineNumber":3,"author":{"gitId":"wanninglim"},"content":"public class PonyoException extends RuntimeException {","lastModifiedDate":"2021-08-25"},{"lineNumber":4,"author":{"gitId":"wanninglim"},"content":"    public PonyoException(String err) {","lastModifiedDate":"2021-08-25"},{"lineNumber":5,"author":{"gitId":"wanninglim"},"content":"        super(err);","lastModifiedDate":"2021-08-25"},{"lineNumber":6,"author":{"gitId":"wanninglim"},"content":"    }","lastModifiedDate":"2021-08-25"},{"lineNumber":7,"author":{"gitId":"wanninglim"},"content":"}","lastModifiedDate":"2021-08-25"}],"authorContributionMap":{"wanninglim":7}},{"path":"src/main/java/ponyo/data/task/Deadline.java","fileType":"java","lines":[{"lineNumber":1,"author":{"gitId":"wanninglim"},"content":"package ponyo.data.task;","lastModifiedDate":"2021-08-25"},{"lineNumber":2,"author":{"gitId":"wanninglim"},"content":"","lastModifiedDate":"2021-08-25"},{"lineNumber":3,"author":{"gitId":"wanninglim"},"content":"public class Deadline extends Task {","lastModifiedDate":"2021-08-18"},{"lineNumber":4,"author":{"gitId":"wanninglim"},"content":"    protected String by;","lastModifiedDate":"2021-08-18"},{"lineNumber":5,"author":{"gitId":"wanninglim"},"content":"","lastModifiedDate":"2021-08-18"},{"lineNumber":6,"author":{"gitId":"wanninglim"},"content":"    public Deadline(String description, String by) {","lastModifiedDate":"2021-08-18"},{"lineNumber":7,"author":{"gitId":"wanninglim"},"content":"        super(description);","lastModifiedDate":"2021-08-18"},{"lineNumber":8,"author":{"gitId":"wanninglim"},"content":"        this.by \u003d by;","lastModifiedDate":"2021-08-18"},{"lineNumber":9,"author":{"gitId":"wanninglim"},"content":"    }","lastModifiedDate":"2021-08-18"},{"lineNumber":10,"author":{"gitId":"wanninglim"},"content":"","lastModifiedDate":"2021-08-18"},{"lineNumber":11,"author":{"gitId":"wanninglim"},"content":"    // File operations","lastModifiedDate":"2021-08-24"},{"lineNumber":12,"author":{"gitId":"wanninglim"},"content":"    @Override","lastModifiedDate":"2021-08-24"},{"lineNumber":13,"author":{"gitId":"wanninglim"},"content":"    public String toStringInFile() {","lastModifiedDate":"2021-08-24"},{"lineNumber":14,"author":{"gitId":"wanninglim"},"content":"        return \"D - \" + super.toStringInFile() + \" - \" + by;","lastModifiedDate":"2021-08-24"},{"lineNumber":15,"author":{"gitId":"wanninglim"},"content":"    }","lastModifiedDate":"2021-08-24"},{"lineNumber":16,"author":{"gitId":"wanninglim"},"content":"","lastModifiedDate":"2021-08-24"},{"lineNumber":17,"author":{"gitId":"wanninglim"},"content":"    @Override","lastModifiedDate":"2021-08-18"},{"lineNumber":18,"author":{"gitId":"wanninglim"},"content":"    public String toString() {","lastModifiedDate":"2021-08-18"},{"lineNumber":19,"author":{"gitId":"wanninglim"},"content":"        return \"[D]\" + super.toString() + \" (by: \" + by + \")\";","lastModifiedDate":"2021-08-18"},{"lineNumber":20,"author":{"gitId":"wanninglim"},"content":"    }","lastModifiedDate":"2021-08-18"},{"lineNumber":21,"author":{"gitId":"wanninglim"},"content":"}","lastModifiedDate":"2021-08-18"}],"authorContributionMap":{"wanninglim":21}},{"path":"src/main/java/ponyo/data/task/Event.java","fileType":"java","lines":[{"lineNumber":1,"author":{"gitId":"wanninglim"},"content":"package ponyo.data.task;","lastModifiedDate":"2021-08-25"},{"lineNumber":2,"author":{"gitId":"wanninglim"},"content":"","lastModifiedDate":"2021-08-25"},{"lineNumber":3,"author":{"gitId":"wanninglim"},"content":"public class Event extends Task {","lastModifiedDate":"2021-08-18"},{"lineNumber":4,"author":{"gitId":"wanninglim"},"content":"    protected String at;","lastModifiedDate":"2021-08-18"},{"lineNumber":5,"author":{"gitId":"wanninglim"},"content":"","lastModifiedDate":"2021-08-18"},{"lineNumber":6,"author":{"gitId":"wanninglim"},"content":"    public Event(String description, String at) {","lastModifiedDate":"2021-08-18"},{"lineNumber":7,"author":{"gitId":"wanninglim"},"content":"        super(description);","lastModifiedDate":"2021-08-18"},{"lineNumber":8,"author":{"gitId":"wanninglim"},"content":"        this.at \u003d at;","lastModifiedDate":"2021-08-18"},{"lineNumber":9,"author":{"gitId":"wanninglim"},"content":"    }","lastModifiedDate":"2021-08-18"},{"lineNumber":10,"author":{"gitId":"wanninglim"},"content":"","lastModifiedDate":"2021-08-18"},{"lineNumber":11,"author":{"gitId":"wanninglim"},"content":"    @Override","lastModifiedDate":"2021-08-24"},{"lineNumber":12,"author":{"gitId":"wanninglim"},"content":"    public String toStringInFile() {","lastModifiedDate":"2021-08-24"},{"lineNumber":13,"author":{"gitId":"wanninglim"},"content":"        return \"E - \" + super.toStringInFile() + \" - \" + at;","lastModifiedDate":"2021-08-24"},{"lineNumber":14,"author":{"gitId":"wanninglim"},"content":"    }","lastModifiedDate":"2021-08-24"},{"lineNumber":15,"author":{"gitId":"wanninglim"},"content":"","lastModifiedDate":"2021-08-24"},{"lineNumber":16,"author":{"gitId":"wanninglim"},"content":"    @Override","lastModifiedDate":"2021-08-18"},{"lineNumber":17,"author":{"gitId":"wanninglim"},"content":"    public String toString() {","lastModifiedDate":"2021-08-18"},{"lineNumber":18,"author":{"gitId":"wanninglim"},"content":"        return \"[E]\" + super.toString() + \" (at: \" + at + \")\";","lastModifiedDate":"2021-08-18"},{"lineNumber":19,"author":{"gitId":"wanninglim"},"content":"    }","lastModifiedDate":"2021-08-18"},{"lineNumber":20,"author":{"gitId":"wanninglim"},"content":"}","lastModifiedDate":"2021-08-18"}],"authorContributionMap":{"wanninglim":20}},{"path":"src/main/java/ponyo/data/task/Task.java","fileType":"java","lines":[{"lineNumber":1,"author":{"gitId":"wanninglim"},"content":"package ponyo.data.task;","lastModifiedDate":"2021-08-25"},{"lineNumber":2,"author":{"gitId":"wanninglim"},"content":"","lastModifiedDate":"2021-08-25"},{"lineNumber":3,"author":{"gitId":"wanninglim"},"content":"public class Task {","lastModifiedDate":"2021-08-18"},{"lineNumber":4,"author":{"gitId":"wanninglim"},"content":"    protected String description;","lastModifiedDate":"2021-08-18"},{"lineNumber":5,"author":{"gitId":"wanninglim"},"content":"    protected boolean isDone;","lastModifiedDate":"2021-08-18"},{"lineNumber":6,"author":{"gitId":"wanninglim"},"content":"","lastModifiedDate":"2021-08-18"},{"lineNumber":7,"author":{"gitId":"wanninglim"},"content":"    public Task(String description) {","lastModifiedDate":"2021-08-18"},{"lineNumber":8,"author":{"gitId":"wanninglim"},"content":"        this.description \u003d description;","lastModifiedDate":"2021-08-18"},{"lineNumber":9,"author":{"gitId":"wanninglim"},"content":"        this.isDone \u003d false;","lastModifiedDate":"2021-08-18"},{"lineNumber":10,"author":{"gitId":"wanninglim"},"content":"    }","lastModifiedDate":"2021-08-18"},{"lineNumber":11,"author":{"gitId":"wanninglim"},"content":"","lastModifiedDate":"2021-08-18"},{"lineNumber":12,"author":{"gitId":"wanninglim"},"content":"    public String getStatusIcon() {","lastModifiedDate":"2021-08-18"},{"lineNumber":13,"author":{"gitId":"wanninglim"},"content":"        return (isDone ? \"X\" : \" \"); // mark done task with X","lastModifiedDate":"2021-08-18"},{"lineNumber":14,"author":{"gitId":"wanninglim"},"content":"    }","lastModifiedDate":"2021-08-18"},{"lineNumber":15,"author":{"gitId":"wanninglim"},"content":"","lastModifiedDate":"2021-08-18"},{"lineNumber":16,"author":{"gitId":"wanninglim"},"content":"    public void markAsDone() {","lastModifiedDate":"2021-08-18"},{"lineNumber":17,"author":{"gitId":"wanninglim"},"content":"        this.isDone \u003d true;","lastModifiedDate":"2021-08-18"},{"lineNumber":18,"author":{"gitId":"wanninglim"},"content":"    }","lastModifiedDate":"2021-08-18"},{"lineNumber":19,"author":{"gitId":"wanninglim"},"content":"","lastModifiedDate":"2021-08-18"},{"lineNumber":20,"author":{"gitId":"wanninglim"},"content":"    // File operations","lastModifiedDate":"2021-08-24"},{"lineNumber":21,"author":{"gitId":"wanninglim"},"content":"    public int getStatusNumber() {","lastModifiedDate":"2021-08-24"},{"lineNumber":22,"author":{"gitId":"wanninglim"},"content":"        return (isDone ? 1 : 0); // mark done task with 1","lastModifiedDate":"2021-08-24"},{"lineNumber":23,"author":{"gitId":"wanninglim"},"content":"    }","lastModifiedDate":"2021-08-24"},{"lineNumber":24,"author":{"gitId":"wanninglim"},"content":"","lastModifiedDate":"2021-08-24"},{"lineNumber":25,"author":{"gitId":"wanninglim"},"content":"    // Sample: D - 0 - return book - June 6th","lastModifiedDate":"2021-08-24"},{"lineNumber":26,"author":{"gitId":"wanninglim"},"content":"    public String toStringInFile() {","lastModifiedDate":"2021-08-24"},{"lineNumber":27,"author":{"gitId":"wanninglim"},"content":"        return String.format(\"%d - %s\", this.getStatusNumber(), this.description);","lastModifiedDate":"2021-08-24"},{"lineNumber":28,"author":{"gitId":"wanninglim"},"content":"    }","lastModifiedDate":"2021-08-24"},{"lineNumber":29,"author":{"gitId":"wanninglim"},"content":"","lastModifiedDate":"2021-08-24"},{"lineNumber":30,"author":{"gitId":"wanninglim"},"content":"    public String toString() {","lastModifiedDate":"2021-08-18"},{"lineNumber":31,"author":{"gitId":"wanninglim"},"content":"        return \"[\" + this.getStatusIcon() + \"] \" + this.description;","lastModifiedDate":"2021-08-18"},{"lineNumber":32,"author":{"gitId":"wanninglim"},"content":"    }","lastModifiedDate":"2021-08-18"},{"lineNumber":33,"author":{"gitId":"wanninglim"},"content":"}","lastModifiedDate":"2021-08-18"}],"authorContributionMap":{"wanninglim":33}},{"path":"src/main/java/ponyo/data/task/TaskList.java","fileType":"java","lines":[{"lineNumber":1,"author":{"gitId":"wanninglim"},"content":"package ponyo.data.task;","lastModifiedDate":"2021-08-25"},{"lineNumber":2,"author":{"gitId":"wanninglim"},"content":"","lastModifiedDate":"2021-08-25"},{"lineNumber":3,"author":{"gitId":"wanninglim"},"content":"import java.util.ArrayList;","lastModifiedDate":"2021-08-25"},{"lineNumber":4,"author":{"gitId":"wanninglim"},"content":"import java.util.List;","lastModifiedDate":"2021-08-25"},{"lineNumber":5,"author":{"gitId":"wanninglim"},"content":"","lastModifiedDate":"2021-08-25"},{"lineNumber":6,"author":{"gitId":"wanninglim"},"content":"public class TaskList {","lastModifiedDate":"2021-08-25"},{"lineNumber":7,"author":{"gitId":"wanninglim"},"content":"    protected List\u003cTask\u003e tasks;","lastModifiedDate":"2021-08-25"},{"lineNumber":8,"author":{"gitId":"wanninglim"},"content":"","lastModifiedDate":"2021-08-25"},{"lineNumber":9,"author":{"gitId":"wanninglim"},"content":"    public TaskList() {","lastModifiedDate":"2021-08-25"},{"lineNumber":10,"author":{"gitId":"wanninglim"},"content":"        this.tasks \u003d new ArrayList\u003c\u003e();","lastModifiedDate":"2021-08-25"},{"lineNumber":11,"author":{"gitId":"wanninglim"},"content":"    }","lastModifiedDate":"2021-08-25"},{"lineNumber":12,"author":{"gitId":"wanninglim"},"content":"","lastModifiedDate":"2021-08-25"},{"lineNumber":13,"author":{"gitId":"wanninglim"},"content":"    public TaskList(ArrayList\u003cTask\u003e tasks) {","lastModifiedDate":"2021-08-25"},{"lineNumber":14,"author":{"gitId":"wanninglim"},"content":"        this.tasks \u003d tasks;","lastModifiedDate":"2021-08-25"},{"lineNumber":15,"author":{"gitId":"wanninglim"},"content":"    }","lastModifiedDate":"2021-08-25"},{"lineNumber":16,"author":{"gitId":"wanninglim"},"content":"","lastModifiedDate":"2021-08-25"},{"lineNumber":17,"author":{"gitId":"wanninglim"},"content":"    public void add(Task task) {","lastModifiedDate":"2021-08-25"},{"lineNumber":18,"author":{"gitId":"wanninglim"},"content":"        tasks.add(task);","lastModifiedDate":"2021-08-25"},{"lineNumber":19,"author":{"gitId":"wanninglim"},"content":"    }","lastModifiedDate":"2021-08-25"},{"lineNumber":20,"author":{"gitId":"wanninglim"},"content":"","lastModifiedDate":"2021-08-25"},{"lineNumber":21,"author":{"gitId":"wanninglim"},"content":"    public void remove(int task) {","lastModifiedDate":"2021-08-25"},{"lineNumber":22,"author":{"gitId":"wanninglim"},"content":"        tasks.remove(task - 1);","lastModifiedDate":"2021-08-25"},{"lineNumber":23,"author":{"gitId":"wanninglim"},"content":"    }","lastModifiedDate":"2021-08-25"},{"lineNumber":24,"author":{"gitId":"wanninglim"},"content":"","lastModifiedDate":"2021-08-25"},{"lineNumber":25,"author":{"gitId":"wanninglim"},"content":"    public Task retrieveTask(int task) {","lastModifiedDate":"2021-08-25"},{"lineNumber":26,"author":{"gitId":"wanninglim"},"content":"        return tasks.get(task - 1);","lastModifiedDate":"2021-08-25"},{"lineNumber":27,"author":{"gitId":"wanninglim"},"content":"    }","lastModifiedDate":"2021-08-25"},{"lineNumber":28,"author":{"gitId":"wanninglim"},"content":"","lastModifiedDate":"2021-08-25"},{"lineNumber":29,"author":{"gitId":"wanninglim"},"content":"    public int size() {","lastModifiedDate":"2021-08-25"},{"lineNumber":30,"author":{"gitId":"wanninglim"},"content":"        return tasks.size();","lastModifiedDate":"2021-08-25"},{"lineNumber":31,"author":{"gitId":"wanninglim"},"content":"    }","lastModifiedDate":"2021-08-25"},{"lineNumber":32,"author":{"gitId":"wanninglim"},"content":"}","lastModifiedDate":"2021-08-25"}],"authorContributionMap":{"wanninglim":32}},{"path":"src/main/java/ponyo/data/task/Todo.java","fileType":"java","lines":[{"lineNumber":1,"author":{"gitId":"wanninglim"},"content":"package ponyo.data.task;","lastModifiedDate":"2021-08-25"},{"lineNumber":2,"author":{"gitId":"wanninglim"},"content":"","lastModifiedDate":"2021-08-25"},{"lineNumber":3,"author":{"gitId":"wanninglim"},"content":"public class Todo extends Task {","lastModifiedDate":"2021-08-18"},{"lineNumber":4,"author":{"gitId":"wanninglim"},"content":"    public Todo(String description) {","lastModifiedDate":"2021-08-18"},{"lineNumber":5,"author":{"gitId":"wanninglim"},"content":"        super(description);","lastModifiedDate":"2021-08-18"},{"lineNumber":6,"author":{"gitId":"wanninglim"},"content":"    }","lastModifiedDate":"2021-08-18"},{"lineNumber":7,"author":{"gitId":"wanninglim"},"content":"","lastModifiedDate":"2021-08-18"},{"lineNumber":8,"author":{"gitId":"wanninglim"},"content":"    // File operations","lastModifiedDate":"2021-08-24"},{"lineNumber":9,"author":{"gitId":"wanninglim"},"content":"    @Override","lastModifiedDate":"2021-08-24"},{"lineNumber":10,"author":{"gitId":"wanninglim"},"content":"    public String toStringInFile() {","lastModifiedDate":"2021-08-24"},{"lineNumber":11,"author":{"gitId":"wanninglim"},"content":"        return \"T - \" + super.toStringInFile();","lastModifiedDate":"2021-08-24"},{"lineNumber":12,"author":{"gitId":"wanninglim"},"content":"    }","lastModifiedDate":"2021-08-24"},{"lineNumber":13,"author":{"gitId":"wanninglim"},"content":"","lastModifiedDate":"2021-08-24"},{"lineNumber":14,"author":{"gitId":"wanninglim"},"content":"    @Override","lastModifiedDate":"2021-08-18"},{"lineNumber":15,"author":{"gitId":"wanninglim"},"content":"    public String toString() {","lastModifiedDate":"2021-08-18"},{"lineNumber":16,"author":{"gitId":"wanninglim"},"content":"        return \"[T]\" + super.toString();","lastModifiedDate":"2021-08-18"},{"lineNumber":17,"author":{"gitId":"wanninglim"},"content":"    }","lastModifiedDate":"2021-08-18"},{"lineNumber":18,"author":{"gitId":"wanninglim"},"content":"}","lastModifiedDate":"2021-08-18"}],"authorContributionMap":{"wanninglim":18}},{"path":"src/main/java/ponyo/parser/Parser.java","fileType":"java","lines":[{"lineNumber":1,"author":{"gitId":"wanninglim"},"content":"package ponyo.parser;","lastModifiedDate":"2021-08-25"},{"lineNumber":2,"author":{"gitId":"wanninglim"},"content":"","lastModifiedDate":"2021-08-25"},{"lineNumber":3,"author":{"gitId":"wanninglim"},"content":"import ponyo.data.exceptions.PonyoException;","lastModifiedDate":"2021-08-25"},{"lineNumber":4,"author":{"gitId":"wanninglim"},"content":"import ponyo.commands.Command;","lastModifiedDate":"2021-08-25"},{"lineNumber":5,"author":{"gitId":"wanninglim"},"content":"import ponyo.commands.ListCommand;","lastModifiedDate":"2021-08-25"},{"lineNumber":6,"author":{"gitId":"wanninglim"},"content":"import ponyo.commands.AddCommand;","lastModifiedDate":"2021-08-25"},{"lineNumber":7,"author":{"gitId":"wanninglim"},"content":"import ponyo.commands.DeleteCommand;","lastModifiedDate":"2021-08-25"},{"lineNumber":8,"author":{"gitId":"wanninglim"},"content":"import ponyo.commands.DoneCommand;","lastModifiedDate":"2021-08-25"},{"lineNumber":9,"author":{"gitId":"wanninglim"},"content":"import ponyo.commands.ExitCommand;","lastModifiedDate":"2021-08-25"},{"lineNumber":10,"author":{"gitId":"wanninglim"},"content":"","lastModifiedDate":"2021-08-25"},{"lineNumber":11,"author":{"gitId":"wanninglim"},"content":"public class Parser {","lastModifiedDate":"2021-08-25"},{"lineNumber":12,"author":{"gitId":"wanninglim"},"content":"    private static final String MESSAGE_IDK \u003d \"\\t☹ OOPS!!! I\u0027m sorry, but I don\u0027t know what that means :-(\";","lastModifiedDate":"2021-08-25"},{"lineNumber":13,"author":{"gitId":"wanninglim"},"content":"","lastModifiedDate":"2021-08-25"},{"lineNumber":14,"author":{"gitId":"wanninglim"},"content":"    public static Command parse(String cmd) {","lastModifiedDate":"2021-08-25"},{"lineNumber":15,"author":{"gitId":"wanninglim"},"content":"        String[] cmds \u003d cmd.split(\" \", 2);","lastModifiedDate":"2021-08-25"},{"lineNumber":16,"author":{"gitId":"wanninglim"},"content":"","lastModifiedDate":"2021-08-25"},{"lineNumber":17,"author":{"gitId":"wanninglim"},"content":"        try {","lastModifiedDate":"2021-08-25"},{"lineNumber":18,"author":{"gitId":"wanninglim"},"content":"            switch (cmds[0]) {","lastModifiedDate":"2021-08-25"},{"lineNumber":19,"author":{"gitId":"wanninglim"},"content":"                case \"list\":","lastModifiedDate":"2021-08-25"},{"lineNumber":20,"author":{"gitId":"wanninglim"},"content":"                    return new ListCommand();","lastModifiedDate":"2021-08-25"},{"lineNumber":21,"author":{"gitId":"wanninglim"},"content":"                case \"bye\":","lastModifiedDate":"2021-08-25"},{"lineNumber":22,"author":{"gitId":"wanninglim"},"content":"                    return new ExitCommand();","lastModifiedDate":"2021-08-25"},{"lineNumber":23,"author":{"gitId":"wanninglim"},"content":"                case \"done\":","lastModifiedDate":"2021-08-25"},{"lineNumber":24,"author":{"gitId":"wanninglim"},"content":"                    return new DoneCommand(Integer.parseInt(cmds[1]));","lastModifiedDate":"2021-08-25"},{"lineNumber":25,"author":{"gitId":"wanninglim"},"content":"                case \"todo\":","lastModifiedDate":"2021-08-25"},{"lineNumber":26,"author":{"gitId":"wanninglim"},"content":"                case \"deadline\":","lastModifiedDate":"2021-08-25"},{"lineNumber":27,"author":{"gitId":"wanninglim"},"content":"                case \"event\":","lastModifiedDate":"2021-08-25"},{"lineNumber":28,"author":{"gitId":"wanninglim"},"content":"                    return new AddCommand(cmds);","lastModifiedDate":"2021-08-25"},{"lineNumber":29,"author":{"gitId":"wanninglim"},"content":"                case \"delete\":","lastModifiedDate":"2021-08-25"},{"lineNumber":30,"author":{"gitId":"wanninglim"},"content":"                    return new DeleteCommand(Integer.parseInt(cmds[1]));","lastModifiedDate":"2021-08-25"},{"lineNumber":31,"author":{"gitId":"wanninglim"},"content":"                default:","lastModifiedDate":"2021-08-25"},{"lineNumber":32,"author":{"gitId":"wanninglim"},"content":"                    throw new PonyoException(\"Invalid command given!\");","lastModifiedDate":"2021-08-25"},{"lineNumber":33,"author":{"gitId":"wanninglim"},"content":"            }","lastModifiedDate":"2021-08-25"},{"lineNumber":34,"author":{"gitId":"wanninglim"},"content":"        } catch (PonyoException e) {","lastModifiedDate":"2021-08-25"},{"lineNumber":35,"author":{"gitId":"wanninglim"},"content":"            throw new PonyoException(MESSAGE_IDK);","lastModifiedDate":"2021-08-25"},{"lineNumber":36,"author":{"gitId":"wanninglim"},"content":"        }","lastModifiedDate":"2021-08-25"},{"lineNumber":37,"author":{"gitId":"wanninglim"},"content":"","lastModifiedDate":"2021-08-25"},{"lineNumber":38,"author":{"gitId":"wanninglim"},"content":"    }","lastModifiedDate":"2021-08-25"},{"lineNumber":39,"author":{"gitId":"wanninglim"},"content":"}","lastModifiedDate":"2021-08-25"}],"authorContributionMap":{"wanninglim":39}},{"path":"src/main/java/ponyo/storage/Storage.java","fileType":"java","lines":[{"lineNumber":1,"author":{"gitId":"wanninglim"},"content":"package ponyo.storage;","lastModifiedDate":"2021-08-25"},{"lineNumber":2,"author":{"gitId":"wanninglim"},"content":"","lastModifiedDate":"2021-08-25"},{"lineNumber":3,"author":{"gitId":"wanninglim"},"content":"import java.io.File;","lastModifiedDate":"2021-08-25"},{"lineNumber":4,"author":{"gitId":"wanninglim"},"content":"import java.io.FileWriter;","lastModifiedDate":"2021-08-25"},{"lineNumber":5,"author":{"gitId":"wanninglim"},"content":"import java.io.IOException;","lastModifiedDate":"2021-08-25"},{"lineNumber":6,"author":{"gitId":"wanninglim"},"content":"","lastModifiedDate":"2021-08-25"},{"lineNumber":7,"author":{"gitId":"wanninglim"},"content":"import java.util.ArrayList;","lastModifiedDate":"2021-08-25"},{"lineNumber":8,"author":{"gitId":"wanninglim"},"content":"import java.util.Scanner;","lastModifiedDate":"2021-08-25"},{"lineNumber":9,"author":{"gitId":"wanninglim"},"content":"import java.util.regex.Pattern;","lastModifiedDate":"2021-08-25"},{"lineNumber":10,"author":{"gitId":"wanninglim"},"content":"","lastModifiedDate":"2021-08-25"},{"lineNumber":11,"author":{"gitId":"wanninglim"},"content":"import ponyo.data.task.Task;","lastModifiedDate":"2021-08-25"},{"lineNumber":12,"author":{"gitId":"wanninglim"},"content":"import ponyo.data.task.TaskList;","lastModifiedDate":"2021-08-25"},{"lineNumber":13,"author":{"gitId":"wanninglim"},"content":"import ponyo.data.task.Todo;","lastModifiedDate":"2021-08-25"},{"lineNumber":14,"author":{"gitId":"wanninglim"},"content":"import ponyo.data.task.Deadline;","lastModifiedDate":"2021-08-25"},{"lineNumber":15,"author":{"gitId":"wanninglim"},"content":"import ponyo.data.task.Event;","lastModifiedDate":"2021-08-25"},{"lineNumber":16,"author":{"gitId":"wanninglim"},"content":"import ponyo.data.exceptions.PonyoException;","lastModifiedDate":"2021-08-25"},{"lineNumber":17,"author":{"gitId":"wanninglim"},"content":"","lastModifiedDate":"2021-08-25"},{"lineNumber":18,"author":{"gitId":"wanninglim"},"content":"","lastModifiedDate":"2021-08-25"},{"lineNumber":19,"author":{"gitId":"wanninglim"},"content":"public class Storage {","lastModifiedDate":"2021-08-25"},{"lineNumber":20,"author":{"gitId":"wanninglim"},"content":"    protected String filePath;","lastModifiedDate":"2021-08-25"},{"lineNumber":21,"author":{"gitId":"wanninglim"},"content":"","lastModifiedDate":"2021-08-25"},{"lineNumber":22,"author":{"gitId":"wanninglim"},"content":"    public Storage(String filePath) {","lastModifiedDate":"2021-08-25"},{"lineNumber":23,"author":{"gitId":"wanninglim"},"content":"        this.filePath \u003d filePath;","lastModifiedDate":"2021-08-25"},{"lineNumber":24,"author":{"gitId":"wanninglim"},"content":"    }","lastModifiedDate":"2021-08-25"},{"lineNumber":25,"author":{"gitId":"wanninglim"},"content":"","lastModifiedDate":"2021-08-25"},{"lineNumber":26,"author":{"gitId":"wanninglim"},"content":"    private static final String PATH \u003d \"src/main/data\";","lastModifiedDate":"2021-08-25"},{"lineNumber":27,"author":{"gitId":"wanninglim"},"content":"    private static final String FILENAME \u003d \"tasks.txt\";","lastModifiedDate":"2021-08-25"},{"lineNumber":28,"author":{"gitId":"wanninglim"},"content":"","lastModifiedDate":"2021-08-25"},{"lineNumber":29,"author":{"gitId":"wanninglim"},"content":"    public ArrayList\u003cTask\u003e load() {","lastModifiedDate":"2021-08-25"},{"lineNumber":30,"author":{"gitId":"wanninglim"},"content":"        try {","lastModifiedDate":"2021-08-25"},{"lineNumber":31,"author":{"gitId":"wanninglim"},"content":"            ArrayList\u003cTask\u003e tasks \u003d new ArrayList();","lastModifiedDate":"2021-08-25"},{"lineNumber":32,"author":{"gitId":"wanninglim"},"content":"            readTasksFromFile(tasks, filePath);","lastModifiedDate":"2021-08-25"},{"lineNumber":33,"author":{"gitId":"wanninglim"},"content":"            return tasks;","lastModifiedDate":"2021-08-25"},{"lineNumber":34,"author":{"gitId":"wanninglim"},"content":"        } catch (IOException e) {","lastModifiedDate":"2021-08-25"},{"lineNumber":35,"author":{"gitId":"wanninglim"},"content":"            throw new PonyoException(\"Error loading from file :(\");","lastModifiedDate":"2021-08-25"},{"lineNumber":36,"author":{"gitId":"wanninglim"},"content":"        }","lastModifiedDate":"2021-08-25"},{"lineNumber":37,"author":{"gitId":"wanninglim"},"content":"","lastModifiedDate":"2021-08-25"},{"lineNumber":38,"author":{"gitId":"wanninglim"},"content":"    }","lastModifiedDate":"2021-08-25"},{"lineNumber":39,"author":{"gitId":"wanninglim"},"content":"","lastModifiedDate":"2021-08-25"},{"lineNumber":40,"author":{"gitId":"wanninglim"},"content":"    // Check if file and folder exists","lastModifiedDate":"2021-08-25"},{"lineNumber":41,"author":{"gitId":"wanninglim"},"content":"    public void fileFolderCheck(String filePath) throws IOException {","lastModifiedDate":"2021-08-25"},{"lineNumber":42,"author":{"gitId":"wanninglim"},"content":"        File file \u003d new File(filePath);","lastModifiedDate":"2021-08-25"},{"lineNumber":43,"author":{"gitId":"wanninglim"},"content":"        File directory \u003d new File(PATH);","lastModifiedDate":"2021-08-25"},{"lineNumber":44,"author":{"gitId":"wanninglim"},"content":"","lastModifiedDate":"2021-08-25"},{"lineNumber":45,"author":{"gitId":"wanninglim"},"content":"        if (!directory.exists()) {","lastModifiedDate":"2021-08-25"},{"lineNumber":46,"author":{"gitId":"wanninglim"},"content":"            directory.mkdir();","lastModifiedDate":"2021-08-25"},{"lineNumber":47,"author":{"gitId":"wanninglim"},"content":"        }","lastModifiedDate":"2021-08-25"},{"lineNumber":48,"author":{"gitId":"wanninglim"},"content":"        if (!file.exists()) {","lastModifiedDate":"2021-08-25"},{"lineNumber":49,"author":{"gitId":"wanninglim"},"content":"            file.createNewFile();","lastModifiedDate":"2021-08-25"},{"lineNumber":50,"author":{"gitId":"wanninglim"},"content":"        }","lastModifiedDate":"2021-08-25"},{"lineNumber":51,"author":{"gitId":"wanninglim"},"content":"    }","lastModifiedDate":"2021-08-25"},{"lineNumber":52,"author":{"gitId":"wanninglim"},"content":"","lastModifiedDate":"2021-08-25"},{"lineNumber":53,"author":{"gitId":"wanninglim"},"content":"    public void readTasksFromFile(ArrayList tasks, String filePath) throws IOException {","lastModifiedDate":"2021-08-25"},{"lineNumber":54,"author":{"gitId":"wanninglim"},"content":"        fileFolderCheck(filePath);","lastModifiedDate":"2021-08-25"},{"lineNumber":55,"author":{"gitId":"wanninglim"},"content":"        Scanner read \u003d new Scanner(new File(filePath));","lastModifiedDate":"2021-08-25"},{"lineNumber":56,"author":{"gitId":"wanninglim"},"content":"        read.useDelimiter(Pattern.compile(\"(\\\\n)| - \"));","lastModifiedDate":"2021-08-25"},{"lineNumber":57,"author":{"gitId":"wanninglim"},"content":"","lastModifiedDate":"2021-08-25"},{"lineNumber":58,"author":{"gitId":"wanninglim"},"content":"        while (read.hasNext()) {","lastModifiedDate":"2021-08-25"},{"lineNumber":59,"author":{"gitId":"wanninglim"},"content":"            String taskCode \u003d read.next();","lastModifiedDate":"2021-08-25"},{"lineNumber":60,"author":{"gitId":"wanninglim"},"content":"","lastModifiedDate":"2021-08-25"},{"lineNumber":61,"author":{"gitId":"wanninglim"},"content":"            switch (taskCode) {","lastModifiedDate":"2021-08-25"},{"lineNumber":62,"author":{"gitId":"wanninglim"},"content":"                case \"T\":","lastModifiedDate":"2021-08-25"},{"lineNumber":63,"author":{"gitId":"wanninglim"},"content":"                    int marked \u003d Integer.parseInt(read.next());","lastModifiedDate":"2021-08-25"},{"lineNumber":64,"author":{"gitId":"wanninglim"},"content":"                    String description \u003d read.next();","lastModifiedDate":"2021-08-25"},{"lineNumber":65,"author":{"gitId":"wanninglim"},"content":"                    Task t \u003d new Todo(description);","lastModifiedDate":"2021-08-25"},{"lineNumber":66,"author":{"gitId":"wanninglim"},"content":"                    if (marked \u003d\u003d 1) {","lastModifiedDate":"2021-08-25"},{"lineNumber":67,"author":{"gitId":"wanninglim"},"content":"                        t.markAsDone();","lastModifiedDate":"2021-08-25"},{"lineNumber":68,"author":{"gitId":"wanninglim"},"content":"                    }","lastModifiedDate":"2021-08-25"},{"lineNumber":69,"author":{"gitId":"wanninglim"},"content":"","lastModifiedDate":"2021-08-25"},{"lineNumber":70,"author":{"gitId":"wanninglim"},"content":"                    tasks.add(t);","lastModifiedDate":"2021-08-25"},{"lineNumber":71,"author":{"gitId":"wanninglim"},"content":"                    break;","lastModifiedDate":"2021-08-25"},{"lineNumber":72,"author":{"gitId":"wanninglim"},"content":"                case \"D\":","lastModifiedDate":"2021-08-25"},{"lineNumber":73,"author":{"gitId":"wanninglim"},"content":"                    marked \u003d Integer.parseInt(read.next());","lastModifiedDate":"2021-08-25"},{"lineNumber":74,"author":{"gitId":"wanninglim"},"content":"                    description \u003d read.next();","lastModifiedDate":"2021-08-25"},{"lineNumber":75,"author":{"gitId":"wanninglim"},"content":"                    String by \u003d read.next();","lastModifiedDate":"2021-08-25"},{"lineNumber":76,"author":{"gitId":"wanninglim"},"content":"                    t \u003d new Deadline(description, by);","lastModifiedDate":"2021-08-25"},{"lineNumber":77,"author":{"gitId":"wanninglim"},"content":"                    if (marked \u003d\u003d 1) {","lastModifiedDate":"2021-08-25"},{"lineNumber":78,"author":{"gitId":"wanninglim"},"content":"                        t.markAsDone();","lastModifiedDate":"2021-08-25"},{"lineNumber":79,"author":{"gitId":"wanninglim"},"content":"                    }","lastModifiedDate":"2021-08-25"},{"lineNumber":80,"author":{"gitId":"wanninglim"},"content":"","lastModifiedDate":"2021-08-25"},{"lineNumber":81,"author":{"gitId":"wanninglim"},"content":"                    tasks.add(t);","lastModifiedDate":"2021-08-25"},{"lineNumber":82,"author":{"gitId":"wanninglim"},"content":"                    break;","lastModifiedDate":"2021-08-25"},{"lineNumber":83,"author":{"gitId":"wanninglim"},"content":"                case \"E\":","lastModifiedDate":"2021-08-25"},{"lineNumber":84,"author":{"gitId":"wanninglim"},"content":"                    marked \u003d Integer.parseInt(read.next());","lastModifiedDate":"2021-08-25"},{"lineNumber":85,"author":{"gitId":"wanninglim"},"content":"                    description \u003d read.next();","lastModifiedDate":"2021-08-25"},{"lineNumber":86,"author":{"gitId":"wanninglim"},"content":"                    String at \u003d read.next();","lastModifiedDate":"2021-08-25"},{"lineNumber":87,"author":{"gitId":"wanninglim"},"content":"                    t \u003d new Event(description, at);","lastModifiedDate":"2021-08-25"},{"lineNumber":88,"author":{"gitId":"wanninglim"},"content":"                    if (marked \u003d\u003d 1) {","lastModifiedDate":"2021-08-25"},{"lineNumber":89,"author":{"gitId":"wanninglim"},"content":"                        t.markAsDone();","lastModifiedDate":"2021-08-25"},{"lineNumber":90,"author":{"gitId":"wanninglim"},"content":"                    }","lastModifiedDate":"2021-08-25"},{"lineNumber":91,"author":{"gitId":"wanninglim"},"content":"","lastModifiedDate":"2021-08-25"},{"lineNumber":92,"author":{"gitId":"wanninglim"},"content":"                    tasks.add(t);","lastModifiedDate":"2021-08-25"},{"lineNumber":93,"author":{"gitId":"wanninglim"},"content":"                    break;","lastModifiedDate":"2021-08-25"},{"lineNumber":94,"author":{"gitId":"wanninglim"},"content":"            }","lastModifiedDate":"2021-08-25"},{"lineNumber":95,"author":{"gitId":"wanninglim"},"content":"        }","lastModifiedDate":"2021-08-25"},{"lineNumber":96,"author":{"gitId":"wanninglim"},"content":"        read.close();","lastModifiedDate":"2021-08-25"},{"lineNumber":97,"author":{"gitId":"wanninglim"},"content":"    }","lastModifiedDate":"2021-08-25"},{"lineNumber":98,"author":{"gitId":"wanninglim"},"content":"","lastModifiedDate":"2021-08-25"},{"lineNumber":99,"author":{"gitId":"wanninglim"},"content":"    public void fileLineToWrite(Task t) {","lastModifiedDate":"2021-08-25"},{"lineNumber":100,"author":{"gitId":"wanninglim"},"content":"        try {","lastModifiedDate":"2021-08-25"},{"lineNumber":101,"author":{"gitId":"wanninglim"},"content":"            appendToFile(PATH + \"/\" + FILENAME, t.toStringInFile() + \"\\n\");","lastModifiedDate":"2021-08-25"},{"lineNumber":102,"author":{"gitId":"wanninglim"},"content":"        } catch (IOException e) {","lastModifiedDate":"2021-08-25"},{"lineNumber":103,"author":{"gitId":"wanninglim"},"content":"            System.out.println(\"Something went wrong: \" + e.getMessage());","lastModifiedDate":"2021-08-25"},{"lineNumber":104,"author":{"gitId":"wanninglim"},"content":"        }","lastModifiedDate":"2021-08-25"},{"lineNumber":105,"author":{"gitId":"wanninglim"},"content":"    }","lastModifiedDate":"2021-08-25"},{"lineNumber":106,"author":{"gitId":"wanninglim"},"content":"","lastModifiedDate":"2021-08-25"},{"lineNumber":107,"author":{"gitId":"wanninglim"},"content":"    public void getFullContents(TaskList tasks) {","lastModifiedDate":"2021-08-25"},{"lineNumber":108,"author":{"gitId":"wanninglim"},"content":"        try {","lastModifiedDate":"2021-08-25"},{"lineNumber":109,"author":{"gitId":"wanninglim"},"content":"            String allContent \u003d \"\";","lastModifiedDate":"2021-08-25"},{"lineNumber":110,"author":{"gitId":"wanninglim"},"content":"            for (int i \u003d 1; i \u003c\u003d tasks.size(); i++) {","lastModifiedDate":"2021-08-25"},{"lineNumber":111,"author":{"gitId":"wanninglim"},"content":"                allContent +\u003d tasks.retrieveTask(i).toStringInFile() + \"\\n\";","lastModifiedDate":"2021-08-25"},{"lineNumber":112,"author":{"gitId":"wanninglim"},"content":"            }","lastModifiedDate":"2021-08-25"},{"lineNumber":113,"author":{"gitId":"wanninglim"},"content":"            overwriteFile(PATH + \"/\" + FILENAME, allContent);","lastModifiedDate":"2021-08-25"},{"lineNumber":114,"author":{"gitId":"wanninglim"},"content":"        } catch (IOException e) {","lastModifiedDate":"2021-08-25"},{"lineNumber":115,"author":{"gitId":"wanninglim"},"content":"            System.out.println(\"Something went wrong: \" + e.getMessage());","lastModifiedDate":"2021-08-25"},{"lineNumber":116,"author":{"gitId":"wanninglim"},"content":"        }","lastModifiedDate":"2021-08-25"},{"lineNumber":117,"author":{"gitId":"wanninglim"},"content":"    }","lastModifiedDate":"2021-08-25"},{"lineNumber":118,"author":{"gitId":"wanninglim"},"content":"","lastModifiedDate":"2021-08-25"},{"lineNumber":119,"author":{"gitId":"wanninglim"},"content":"    public void appendToFile(String filePath, String textToAppend) throws IOException {","lastModifiedDate":"2021-08-25"},{"lineNumber":120,"author":{"gitId":"wanninglim"},"content":"        fileFolderCheck(filePath);","lastModifiedDate":"2021-08-25"},{"lineNumber":121,"author":{"gitId":"wanninglim"},"content":"        FileWriter fw \u003d new FileWriter(filePath, true); // create a FileWriter in append mode","lastModifiedDate":"2021-08-25"},{"lineNumber":122,"author":{"gitId":"wanninglim"},"content":"        fw.write(textToAppend);","lastModifiedDate":"2021-08-25"},{"lineNumber":123,"author":{"gitId":"wanninglim"},"content":"        fw.close();","lastModifiedDate":"2021-08-25"},{"lineNumber":124,"author":{"gitId":"wanninglim"},"content":"    }","lastModifiedDate":"2021-08-25"},{"lineNumber":125,"author":{"gitId":"wanninglim"},"content":"","lastModifiedDate":"2021-08-25"},{"lineNumber":126,"author":{"gitId":"wanninglim"},"content":"    public void overwriteFile(String filePath, String fileContent) throws IOException {","lastModifiedDate":"2021-08-25"},{"lineNumber":127,"author":{"gitId":"wanninglim"},"content":"        fileFolderCheck(filePath);","lastModifiedDate":"2021-08-25"},{"lineNumber":128,"author":{"gitId":"wanninglim"},"content":"        FileWriter fw \u003d new FileWriter(filePath); // create a FileWriter","lastModifiedDate":"2021-08-25"},{"lineNumber":129,"author":{"gitId":"wanninglim"},"content":"        fw.write(fileContent);","lastModifiedDate":"2021-08-25"},{"lineNumber":130,"author":{"gitId":"wanninglim"},"content":"        fw.close();","lastModifiedDate":"2021-08-25"},{"lineNumber":131,"author":{"gitId":"wanninglim"},"content":"    }","lastModifiedDate":"2021-08-25"},{"lineNumber":132,"author":{"gitId":"wanninglim"},"content":"}","lastModifiedDate":"2021-08-25"}],"authorContributionMap":{"wanninglim":132}},{"path":"src/main/java/ponyo/ui/Ui.java","fileType":"java","lines":[{"lineNumber":1,"author":{"gitId":"wanninglim"},"content":"package ponyo.ui;","lastModifiedDate":"2021-08-25"},{"lineNumber":2,"author":{"gitId":"wanninglim"},"content":"","lastModifiedDate":"2021-08-25"},{"lineNumber":3,"author":{"gitId":"wanninglim"},"content":"import java.util.Scanner;","lastModifiedDate":"2021-08-25"},{"lineNumber":4,"author":{"gitId":"wanninglim"},"content":"import java.io.InputStream;","lastModifiedDate":"2021-08-25"},{"lineNumber":5,"author":{"gitId":"wanninglim"},"content":"import java.io.PrintStream;","lastModifiedDate":"2021-08-25"},{"lineNumber":6,"author":{"gitId":"wanninglim"},"content":"","lastModifiedDate":"2021-08-25"},{"lineNumber":7,"author":{"gitId":"wanninglim"},"content":"public class Ui {","lastModifiedDate":"2021-08-25"},{"lineNumber":8,"author":{"gitId":"wanninglim"},"content":"    private static final String DIVIDER \u003d \"____________________________________________________________\";","lastModifiedDate":"2021-08-25"},{"lineNumber":9,"author":{"gitId":"wanninglim"},"content":"","lastModifiedDate":"2021-08-25"},{"lineNumber":10,"author":{"gitId":"wanninglim"},"content":"    private static final String CMD_DIVIDER \u003d \"\\t____________________________________________________________\";","lastModifiedDate":"2021-08-25"},{"lineNumber":11,"author":{"gitId":"wanninglim"},"content":"","lastModifiedDate":"2021-08-25"},{"lineNumber":12,"author":{"gitId":"wanninglim"},"content":"    private static final String LOGO \u003d","lastModifiedDate":"2021-08-25"},{"lineNumber":13,"author":{"gitId":"wanninglim"},"content":"            \"    ____    ____    ____    __  __   ____ \\n\" +","lastModifiedDate":"2021-08-25"},{"lineNumber":14,"author":{"gitId":"wanninglim"},"content":"            \"   / __ \\\\  / __ \\\\  / __ \\\\  / / / /  / __ \\\\\\n\" +","lastModifiedDate":"2021-08-25"},{"lineNumber":15,"author":{"gitId":"wanninglim"},"content":"            \"  / /_/ / / /_/ / / / / / / /_/ /  / /_/ /\\n\" +","lastModifiedDate":"2021-08-25"},{"lineNumber":16,"author":{"gitId":"wanninglim"},"content":"            \" / .___/  \\\\____/ /_/ /_/  \\\\__, /   \\\\____/ \\n\" +","lastModifiedDate":"2021-08-25"},{"lineNumber":17,"author":{"gitId":"wanninglim"},"content":"            \"/_/                      /____/           \\n\";","lastModifiedDate":"2021-08-25"},{"lineNumber":18,"author":{"gitId":"wanninglim"},"content":"","lastModifiedDate":"2021-08-25"},{"lineNumber":19,"author":{"gitId":"wanninglim"},"content":"    private final Scanner in;","lastModifiedDate":"2021-08-25"},{"lineNumber":20,"author":{"gitId":"wanninglim"},"content":"    private final PrintStream out;","lastModifiedDate":"2021-08-25"},{"lineNumber":21,"author":{"gitId":"wanninglim"},"content":"","lastModifiedDate":"2021-08-25"},{"lineNumber":22,"author":{"gitId":"wanninglim"},"content":"    public Ui() {","lastModifiedDate":"2021-08-25"},{"lineNumber":23,"author":{"gitId":"wanninglim"},"content":"        this(System.in, System.out);","lastModifiedDate":"2021-08-25"},{"lineNumber":24,"author":{"gitId":"wanninglim"},"content":"    }","lastModifiedDate":"2021-08-25"},{"lineNumber":25,"author":{"gitId":"wanninglim"},"content":"","lastModifiedDate":"2021-08-25"},{"lineNumber":26,"author":{"gitId":"wanninglim"},"content":"    public Ui(InputStream in, PrintStream out) {","lastModifiedDate":"2021-08-25"},{"lineNumber":27,"author":{"gitId":"wanninglim"},"content":"        this.in \u003d new Scanner(in);","lastModifiedDate":"2021-08-25"},{"lineNumber":28,"author":{"gitId":"wanninglim"},"content":"        this.out \u003d out;","lastModifiedDate":"2021-08-25"},{"lineNumber":29,"author":{"gitId":"wanninglim"},"content":"    }","lastModifiedDate":"2021-08-25"},{"lineNumber":30,"author":{"gitId":"wanninglim"},"content":"","lastModifiedDate":"2021-08-25"},{"lineNumber":31,"author":{"gitId":"wanninglim"},"content":"    public void showWelcomeMessage() {","lastModifiedDate":"2021-08-25"},{"lineNumber":32,"author":{"gitId":"wanninglim"},"content":"        show(LOGO,","lastModifiedDate":"2021-08-25"},{"lineNumber":33,"author":{"gitId":"wanninglim"},"content":"                \"Hello! I\u0027m Ponyo.\",","lastModifiedDate":"2021-08-25"},{"lineNumber":34,"author":{"gitId":"wanninglim"},"content":"                \"What can I do for you?\",","lastModifiedDate":"2021-08-25"},{"lineNumber":35,"author":{"gitId":"wanninglim"},"content":"                DIVIDER);","lastModifiedDate":"2021-08-25"},{"lineNumber":36,"author":{"gitId":"wanninglim"},"content":"    }","lastModifiedDate":"2021-08-25"},{"lineNumber":37,"author":{"gitId":"wanninglim"},"content":"","lastModifiedDate":"2021-08-25"},{"lineNumber":38,"author":{"gitId":"wanninglim"},"content":"    public void showLoadingError() {","lastModifiedDate":"2021-08-25"},{"lineNumber":39,"author":{"gitId":"wanninglim"},"content":"        show(\"There was an error while loading your tasks.\");","lastModifiedDate":"2021-08-25"},{"lineNumber":40,"author":{"gitId":"wanninglim"},"content":"    }","lastModifiedDate":"2021-08-25"},{"lineNumber":41,"author":{"gitId":"wanninglim"},"content":"","lastModifiedDate":"2021-08-25"},{"lineNumber":42,"author":{"gitId":"wanninglim"},"content":"    public String readCommand() {","lastModifiedDate":"2021-08-25"},{"lineNumber":43,"author":{"gitId":"wanninglim"},"content":"        return in.nextLine();","lastModifiedDate":"2021-08-25"},{"lineNumber":44,"author":{"gitId":"wanninglim"},"content":"    }","lastModifiedDate":"2021-08-25"},{"lineNumber":45,"author":{"gitId":"wanninglim"},"content":"","lastModifiedDate":"2021-08-25"},{"lineNumber":46,"author":{"gitId":"wanninglim"},"content":"    public void showLine() {","lastModifiedDate":"2021-08-25"},{"lineNumber":47,"author":{"gitId":"wanninglim"},"content":"        show(CMD_DIVIDER);","lastModifiedDate":"2021-08-25"},{"lineNumber":48,"author":{"gitId":"wanninglim"},"content":"    }","lastModifiedDate":"2021-08-25"},{"lineNumber":49,"author":{"gitId":"wanninglim"},"content":"","lastModifiedDate":"2021-08-25"},{"lineNumber":50,"author":{"gitId":"wanninglim"},"content":"    public void showError(String msg) {","lastModifiedDate":"2021-08-25"},{"lineNumber":51,"author":{"gitId":"wanninglim"},"content":"        show(msg);","lastModifiedDate":"2021-08-25"},{"lineNumber":52,"author":{"gitId":"wanninglim"},"content":"    }","lastModifiedDate":"2021-08-25"},{"lineNumber":53,"author":{"gitId":"wanninglim"},"content":"","lastModifiedDate":"2021-08-25"},{"lineNumber":54,"author":{"gitId":"wanninglim"},"content":"    public void show(String... msg) {","lastModifiedDate":"2021-08-25"},{"lineNumber":55,"author":{"gitId":"wanninglim"},"content":"        for (String m : msg) {","lastModifiedDate":"2021-08-25"},{"lineNumber":56,"author":{"gitId":"wanninglim"},"content":"            out.println(m);","lastModifiedDate":"2021-08-25"},{"lineNumber":57,"author":{"gitId":"wanninglim"},"content":"        }","lastModifiedDate":"2021-08-25"},{"lineNumber":58,"author":{"gitId":"wanninglim"},"content":"    }","lastModifiedDate":"2021-08-25"},{"lineNumber":59,"author":{"gitId":"wanninglim"},"content":"}","lastModifiedDate":"2021-08-25"}],"authorContributionMap":{"wanninglim":59}},{"path":"src/test/java/ponyo/commands/AddCommandTest.java","fileType":"java","lines":[{"lineNumber":1,"author":{"gitId":"wanninglim"},"content":"package ponyo.commands;","lastModifiedDate":"2021-08-25"},{"lineNumber":2,"author":{"gitId":"wanninglim"},"content":"","lastModifiedDate":"2021-08-25"},{"lineNumber":3,"author":{"gitId":"wanninglim"},"content":"import org.junit.jupiter.api.Test;","lastModifiedDate":"2021-08-25"},{"lineNumber":4,"author":{"gitId":"wanninglim"},"content":"","lastModifiedDate":"2021-08-25"},{"lineNumber":5,"author":{"gitId":"wanninglim"},"content":"import static org.junit.jupiter.api.Assertions.fail;","lastModifiedDate":"2021-08-25"},{"lineNumber":6,"author":{"gitId":"wanninglim"},"content":"","lastModifiedDate":"2021-08-25"},{"lineNumber":7,"author":{"gitId":"wanninglim"},"content":"import ponyo.data.task.Deadline;","lastModifiedDate":"2021-08-25"},{"lineNumber":8,"author":{"gitId":"wanninglim"},"content":"","lastModifiedDate":"2021-08-25"},{"lineNumber":9,"author":{"gitId":"wanninglim"},"content":"import java.time.format.DateTimeParseException;","lastModifiedDate":"2021-08-25"},{"lineNumber":10,"author":{"gitId":"wanninglim"},"content":"","lastModifiedDate":"2021-08-25"},{"lineNumber":11,"author":{"gitId":"wanninglim"},"content":"public class AddCommandTest {","lastModifiedDate":"2021-08-25"},{"lineNumber":12,"author":{"gitId":"wanninglim"},"content":"    @Test","lastModifiedDate":"2021-08-25"},{"lineNumber":13,"author":{"gitId":"wanninglim"},"content":"    public void addCommand_invalidDateForDeadline_throwsException() {","lastModifiedDate":"2021-08-25"},{"lineNumber":14,"author":{"gitId":"wanninglim"},"content":"        final String[] invalidDates \u003d {\"2020/10/12\"};","lastModifiedDate":"2021-08-25"},{"lineNumber":15,"author":{"gitId":"wanninglim"},"content":"        for (String date : invalidDates) {","lastModifiedDate":"2021-08-25"},{"lineNumber":16,"author":{"gitId":"wanninglim"},"content":"            try {","lastModifiedDate":"2021-08-25"},{"lineNumber":17,"author":{"gitId":"wanninglim"},"content":"                new Deadline(\"example description\", date);","lastModifiedDate":"2021-08-25"},{"lineNumber":18,"author":{"gitId":"wanninglim"},"content":"            } catch (DateTimeParseException e) {","lastModifiedDate":"2021-08-25"},{"lineNumber":19,"author":{"gitId":"wanninglim"},"content":"                return;","lastModifiedDate":"2021-08-25"},{"lineNumber":20,"author":{"gitId":"wanninglim"},"content":"            }","lastModifiedDate":"2021-08-25"},{"lineNumber":21,"author":{"gitId":"wanninglim"},"content":"        }","lastModifiedDate":"2021-08-25"},{"lineNumber":22,"author":{"gitId":"wanninglim"},"content":"        fail(\"A task has been added with an invalid date.\");","lastModifiedDate":"2021-08-25"},{"lineNumber":23,"author":{"gitId":"wanninglim"},"content":"    }","lastModifiedDate":"2021-08-25"},{"lineNumber":24,"author":{"gitId":"wanninglim"},"content":"","lastModifiedDate":"2021-08-25"},{"lineNumber":25,"author":{"gitId":"wanninglim"},"content":"    @Test","lastModifiedDate":"2021-08-25"},{"lineNumber":26,"author":{"gitId":"wanninglim"},"content":"    public void addCommand_invalidDescription_throwsException() {","lastModifiedDate":"2021-08-25"},{"lineNumber":27,"author":{"gitId":"wanninglim"},"content":"        final String[] invalidDescription \u003d {\"\"};","lastModifiedDate":"2021-08-25"},{"lineNumber":28,"author":{"gitId":"wanninglim"},"content":"        for (String desc : invalidDescription) {","lastModifiedDate":"2021-08-25"},{"lineNumber":29,"author":{"gitId":"wanninglim"},"content":"            try {","lastModifiedDate":"2021-08-25"},{"lineNumber":30,"author":{"gitId":"wanninglim"},"content":"                new Deadline(desc, \"2020-10-12\");","lastModifiedDate":"2021-08-25"},{"lineNumber":31,"author":{"gitId":"wanninglim"},"content":"            } catch (ArrayIndexOutOfBoundsException e) {","lastModifiedDate":"2021-08-25"},{"lineNumber":32,"author":{"gitId":"wanninglim"},"content":"                return;","lastModifiedDate":"2021-08-25"},{"lineNumber":33,"author":{"gitId":"wanninglim"},"content":"            }","lastModifiedDate":"2021-08-25"},{"lineNumber":34,"author":{"gitId":"wanninglim"},"content":"        }","lastModifiedDate":"2021-08-25"},{"lineNumber":35,"author":{"gitId":"wanninglim"},"content":"        fail(\"A task has been added with an invalid description.\");","lastModifiedDate":"2021-08-25"},{"lineNumber":36,"author":{"gitId":"wanninglim"},"content":"    }","lastModifiedDate":"2021-08-25"},{"lineNumber":37,"author":{"gitId":"wanninglim"},"content":"}","lastModifiedDate":"2021-08-25"}],"authorContributionMap":{"wanninglim":37}},{"path":"src/test/java/ponyo/data/task/TaskListTest.java","fileType":"java","lines":[{"lineNumber":1,"author":{"gitId":"wanninglim"},"content":"package ponyo.data.task;","lastModifiedDate":"2021-08-25"},{"lineNumber":2,"author":{"gitId":"wanninglim"},"content":"","lastModifiedDate":"2021-08-25"},{"lineNumber":3,"author":{"gitId":"wanninglim"},"content":"import org.junit.jupiter.api.Test;","lastModifiedDate":"2021-08-25"},{"lineNumber":4,"author":{"gitId":"wanninglim"},"content":"","lastModifiedDate":"2021-08-25"},{"lineNumber":5,"author":{"gitId":"wanninglim"},"content":"import java.util.ArrayList;","lastModifiedDate":"2021-08-25"},{"lineNumber":6,"author":{"gitId":"wanninglim"},"content":"","lastModifiedDate":"2021-08-25"},{"lineNumber":7,"author":{"gitId":"wanninglim"},"content":"import static org.junit.jupiter.api.Assertions.assertEquals;","lastModifiedDate":"2021-08-25"},{"lineNumber":8,"author":{"gitId":"wanninglim"},"content":"","lastModifiedDate":"2021-08-25"},{"lineNumber":9,"author":{"gitId":"wanninglim"},"content":"public class TaskListTest {","lastModifiedDate":"2021-08-25"},{"lineNumber":10,"author":{"gitId":"wanninglim"},"content":"    @Test","lastModifiedDate":"2021-08-25"},{"lineNumber":11,"author":{"gitId":"wanninglim"},"content":"    public void taskListTest_correctElementUsingRetrieve() {","lastModifiedDate":"2021-08-25"},{"lineNumber":12,"author":{"gitId":"wanninglim"},"content":"        ArrayList\u003cTask\u003e tasks \u003d new ArrayList\u003c\u003e();","lastModifiedDate":"2021-08-25"},{"lineNumber":13,"author":{"gitId":"wanninglim"},"content":"        tasks.add(new Todo(\"task 1\"));","lastModifiedDate":"2021-08-25"},{"lineNumber":14,"author":{"gitId":"wanninglim"},"content":"        tasks.add(new Todo(\"task 2\"));","lastModifiedDate":"2021-08-25"},{"lineNumber":15,"author":{"gitId":"wanninglim"},"content":"","lastModifiedDate":"2021-08-25"},{"lineNumber":16,"author":{"gitId":"wanninglim"},"content":"        TaskList ponyo \u003d new TaskList(tasks);","lastModifiedDate":"2021-08-25"},{"lineNumber":17,"author":{"gitId":"wanninglim"},"content":"        assertEquals(tasks.get(1), ponyo.retrieveTask(2));","lastModifiedDate":"2021-08-25"},{"lineNumber":18,"author":{"gitId":"wanninglim"},"content":"    }","lastModifiedDate":"2021-08-25"},{"lineNumber":19,"author":{"gitId":"wanninglim"},"content":"}","lastModifiedDate":"2021-08-25"}],"authorContributionMap":{"wanninglim":19}},{"path":"src/test/java/ponyo/parser/ParserTest.java","fileType":"java","lines":[{"lineNumber":1,"author":{"gitId":"wanninglim"},"content":"package ponyo.parser;","lastModifiedDate":"2021-08-25"},{"lineNumber":2,"author":{"gitId":"wanninglim"},"content":"","lastModifiedDate":"2021-08-25"},{"lineNumber":3,"author":{"gitId":"wanninglim"},"content":"import org.junit.jupiter.api.Test;","lastModifiedDate":"2021-08-25"},{"lineNumber":4,"author":{"gitId":"wanninglim"},"content":"","lastModifiedDate":"2021-08-25"},{"lineNumber":5,"author":{"gitId":"wanninglim"},"content":"public class ParserTest {","lastModifiedDate":"2021-08-25"},{"lineNumber":6,"author":{"gitId":"wanninglim"},"content":"}","lastModifiedDate":"2021-08-25"}],"authorContributionMap":{"wanninglim":6}},{"path":"text-ui-test/input.txt","fileType":"txt","lines":[{"lineNumber":1,"author":{"gitId":"wanninglim"},"content":"todo read book","lastModifiedDate":"2021-08-18"},{"lineNumber":2,"author":{"gitId":"wanninglim"},"content":"deadline return book /by June 6th","lastModifiedDate":"2021-08-18"},{"lineNumber":3,"author":{"gitId":"wanninglim"},"content":"event project meeting /at Aug 6th 2-4pm","lastModifiedDate":"2021-08-18"},{"lineNumber":4,"author":{"gitId":"wanninglim"},"content":"done 1","lastModifiedDate":"2021-08-18"},{"lineNumber":5,"author":{"gitId":"wanninglim"},"content":"todo join sports club","lastModifiedDate":"2021-08-18"},{"lineNumber":6,"author":{"gitId":"wanninglim"},"content":"done 4","lastModifiedDate":"2021-08-18"},{"lineNumber":7,"author":{"gitId":"wanninglim"},"content":"todo borrow book","lastModifiedDate":"2021-08-18"},{"lineNumber":8,"author":{"gitId":"wanninglim"},"content":"deadline return book /by Sunday","lastModifiedDate":"2021-08-18"},{"lineNumber":9,"author":{"gitId":"wanninglim"},"content":"event project meeting /at Mon 2-4pm","lastModifiedDate":"2021-08-18"},{"lineNumber":10,"author":{"gitId":"wanninglim"},"content":"list","lastModifiedDate":"2021-08-18"},{"lineNumber":11,"author":{"gitId":"wanninglim"},"content":"bye","lastModifiedDate":"2021-08-18"}],"authorContributionMap":{"wanninglim":11}}]
