{"authorDailyContributionsMap":{"jonas-chow":[{"date":"2021-08-15","commitResults":[{"hash":"bc18a47ba397a8edd89d837ec143d7ecbabe46af","messageTitle":"Add Greet, Echo, Exit functionality","messageBody":"","tags":["Level-1"],"fileTypesAndContributionMap":{"java":{"insertions":29,"deletions":6}}},{"hash":"f5f27985f5c4358604741e509044438891f0bb7b","messageTitle":"Add Add, List functionality","messageBody":"","tags":["Level-2"],"fileTypesAndContributionMap":{"java":{"insertions":31,"deletions":2}}},{"hash":"efa526204ce68fdab15282750c9a2e5c2bdf33b6","messageTitle":"Add Mark as Done functionality","messageBody":"","tags":["Level-3"],"fileTypesAndContributionMap":{"java":{"insertions":60,"deletions":15}}},{"hash":"ba466f84ba30c941db8d037a20e0e25eab39c296","messageTitle":"Add ToDo, Event, Deadline functionality","messageBody":"","tags":["Level-4"],"fileTypesAndContributionMap":{"java":{"insertions":89,"deletions":20}}},{"hash":"90be3f0d8cf51f1724d6a4c3bbb4a054184a7209","messageTitle":"Add Automated Text UI Testing functionality","messageBody":"","tags":["A-TextUITesting"],"fileTypesAndContributionMap":{"txt":{"insertions":14,"deletions":0},"java":{"insertions":2,"deletions":1}}}]},{"date":"2021-08-18","commitResults":[{"hash":"6bd8b33cecdf2c9f3cde80705a6bb56a4d5f1762","messageTitle":"Add Handle Errors functionality","messageBody":"","tags":["Level-5"],"fileTypesAndContributionMap":{"java":{"insertions":95,"deletions":30}}},{"hash":"30bfbd5e34066b478d5379ec2bd0a3b542bd3a69","messageTitle":"Add Delete functionality, updated testcases","messageBody":"","tags":["Level-6"],"fileTypesAndContributionMap":{"txt":{"insertions":3,"deletions":1},"java":{"insertions":40,"deletions":21}}},{"hash":"684bc5123fdaeb42cd2886e727365dbabc71d293","messageTitle":"Added Use Enums functionality","messageBody":"","tags":["A-Enums"],"fileTypesAndContributionMap":{"java":{"insertions":55,"deletions":27}}}]},{"date":"2021-08-22","commitResults":[{"hash":"b0617aa5efeab633213a61b92d3455af50370ee1","messageTitle":"Add Save functionality","messageBody":"","fileTypesAndContributionMap":{"java":{"insertions":142,"deletions":6}}}]},{"date":"2021-08-23","commitResults":[{"hash":"a4d9eb514b98d7b4c84ee34ca86344568a5ecb99","messageTitle":"Add Dates and Times functionality","messageBody":"","fileTypesAndContributionMap":{"java":{"insertions":134,"deletions":27}}},{"hash":"bc28c9a5890dfcec31b85b172eb06ce0d734cb72","messageTitle":"Fix bugs from merging","messageBody":"","fileTypesAndContributionMap":{"java":{"insertions":8,"deletions":7}}}]}]},"authorFileTypeContributionMap":{"jonas-chow":{"java":529,"md":0,"fxml":0,"sh":0,"bat":0,"gradle":0,"txt":16}},"authorContributionVariance":{"jonas-chow":9956.223},"authorDisplayNameMap":{"jonas-chow":"CS2103T-W08-2 CHOW..ONAS"}}
