{"authorDailyContributionsMap":{"itsyme":[{"date":"2021-08-14","commitResults":[{"hash":"100eff78fe873c1e47dd4cd2bfc3e6815687adf7","messageTitle":"Level-1","messageBody":"","tags":["Level-1"],"fileTypesAndContributionMap":{"java":{"insertions":14,"deletions":0}}},{"hash":"0872c9681a072a99eac8cf1b8a317045b90ffccb","messageTitle":"Level-2","messageBody":"","tags":["Level-2"],"fileTypesAndContributionMap":{"java":{"insertions":11,"deletions":1}}},{"hash":"3978a0a91a7a9a58f1e53d8e25b6293ca4a7c046","messageTitle":"Level-3","messageBody":"","tags":["Level-3"],"fileTypesAndContributionMap":{"java":{"insertions":74,"deletions":7}}}]},{"date":"2021-08-15","commitResults":[{"hash":"384df42fe57cb8efe0699efac0abd3beeda021f7","messageTitle":"Level-4","messageBody":"","tags":["Level-4"],"fileTypesAndContributionMap":{"java":{"insertions":118,"deletions":19}}},{"hash":"3b8fdd0ebc6e2b852a26a13b4ea0f5dda4f07ac1","messageTitle":"A-TextUITesting","messageBody":"","tags":["A-TextUITesting"],"fileTypesAndContributionMap":{"txt":{"insertions":9,"deletions":0},"java":{"insertions":6,"deletions":6}}},{"hash":"6a156cfcc14ecf4785bea299e08fa87c2be7a4e9","messageTitle":"Add Level-5","messageBody":"","tags":["Level-5"],"fileTypesAndContributionMap":{"java":{"insertions":91,"deletions":19}}},{"hash":"ffb10c71a5728f35d4bb4028e5f11214d6869863","messageTitle":"Add Level-6","messageBody":"","tags":["Level-6"],"fileTypesAndContributionMap":{"txt":{"insertions":4,"deletions":0},"java":{"insertions":24,"deletions":5}}}]}]},"authorFileTypeContributionMap":{"itsyme":{"java":281,"md":0,"fxml":0,"sh":0,"bat":0,"gradle":0,"txt":13}},"authorContributionVariance":{"itsyme":11181.347},"authorDisplayNameMap":{"itsyme":"LEE ..AVID"}}
