[{"path":"src/main/java/Deadline.java","fileType":"java","lines":[{"lineNumber":1,"author":{"gitId":"wonyeji"},"content":"public class Deadline extends Task {","lastModifiedDate":"2021-08-19"},{"lineNumber":2,"author":{"gitId":"wonyeji"},"content":"","lastModifiedDate":"2021-08-19"},{"lineNumber":3,"author":{"gitId":"wonyeji"},"content":"    protected String by;","lastModifiedDate":"2021-08-19"},{"lineNumber":4,"author":{"gitId":"wonyeji"},"content":"","lastModifiedDate":"2021-08-19"},{"lineNumber":5,"author":{"gitId":"wonyeji"},"content":"    public Deadline(String description, String by) {","lastModifiedDate":"2021-08-19"},{"lineNumber":6,"author":{"gitId":"wonyeji"},"content":"        super(description);","lastModifiedDate":"2021-08-19"},{"lineNumber":7,"author":{"gitId":"wonyeji"},"content":"        this.by \u003d by;","lastModifiedDate":"2021-08-19"},{"lineNumber":8,"author":{"gitId":"wonyeji"},"content":"    }","lastModifiedDate":"2021-08-19"},{"lineNumber":9,"author":{"gitId":"wonyeji"},"content":"","lastModifiedDate":"2021-08-19"},{"lineNumber":10,"author":{"gitId":"wonyeji"},"content":"    @Override","lastModifiedDate":"2021-08-19"},{"lineNumber":11,"author":{"gitId":"wonyeji"},"content":"    public String toString() {","lastModifiedDate":"2021-08-19"},{"lineNumber":12,"author":{"gitId":"wonyeji"},"content":"        return \"[D]\" + super.toString() + \" (by: \" + by + \")\";","lastModifiedDate":"2021-08-19"},{"lineNumber":13,"author":{"gitId":"wonyeji"},"content":"    }","lastModifiedDate":"2021-08-19"},{"lineNumber":14,"author":{"gitId":"wonyeji"},"content":"}","lastModifiedDate":"2021-08-19"}],"authorContributionMap":{"wonyeji":14}},{"path":"src/main/java/Duke.java","fileType":"java","lines":[{"lineNumber":1,"author":{"gitId":"wonyeji"},"content":"import java.util.Scanner;","lastModifiedDate":"2021-08-19"},{"lineNumber":2,"author":{"gitId":"wonyeji"},"content":"import java.util.ArrayList;","lastModifiedDate":"2021-08-19"},{"lineNumber":3,"author":{"gitId":"wonyeji"},"content":"","lastModifiedDate":"2021-08-19"},{"lineNumber":4,"author":{"gitId":"-"},"content":"public class Duke {","lastModifiedDate":"2019-07-29"},{"lineNumber":5,"author":{"gitId":"wonyeji"},"content":"    private static ArrayList\u003cTask\u003e list \u003d new ArrayList\u003cTask\u003e();","lastModifiedDate":"2021-08-19"},{"lineNumber":6,"author":{"gitId":"wonyeji"},"content":"    private static DukeException dukeExp \u003d new DukeException();","lastModifiedDate":"2021-08-19"},{"lineNumber":7,"author":{"gitId":"wonyeji"},"content":"","lastModifiedDate":"2021-08-19"},{"lineNumber":8,"author":{"gitId":"wonyeji"},"content":"    public static void printList() {","lastModifiedDate":"2021-08-19"},{"lineNumber":9,"author":{"gitId":"wonyeji"},"content":"        System.out.println(\"Here are the tasks in your list:\");","lastModifiedDate":"2021-08-19"},{"lineNumber":10,"author":{"gitId":"wonyeji"},"content":"        for (int i \u003d 0; i \u003c list.size(); i++)","lastModifiedDate":"2021-08-19"},{"lineNumber":11,"author":{"gitId":"wonyeji"},"content":"        {","lastModifiedDate":"2021-08-19"},{"lineNumber":12,"author":{"gitId":"wonyeji"},"content":"            System.out.println((i + 1) + \". \" + list.get(i).toString());","lastModifiedDate":"2021-08-19"},{"lineNumber":13,"author":{"gitId":"wonyeji"},"content":"        }","lastModifiedDate":"2021-08-19"},{"lineNumber":14,"author":{"gitId":"wonyeji"},"content":"    }","lastModifiedDate":"2021-08-19"},{"lineNumber":15,"author":{"gitId":"wonyeji"},"content":"","lastModifiedDate":"2021-08-19"},{"lineNumber":16,"author":{"gitId":"wonyeji"},"content":"    public static void printNoOfTasks() {","lastModifiedDate":"2021-08-19"},{"lineNumber":17,"author":{"gitId":"wonyeji"},"content":"        int count \u003d list.size();","lastModifiedDate":"2021-08-19"},{"lineNumber":18,"author":{"gitId":"wonyeji"},"content":"        System.out.println(\"Now you have \" + count + \" tasks in the list.\");","lastModifiedDate":"2021-08-19"},{"lineNumber":19,"author":{"gitId":"wonyeji"},"content":"    }","lastModifiedDate":"2021-08-19"},{"lineNumber":20,"author":{"gitId":"wonyeji"},"content":"","lastModifiedDate":"2021-08-19"},{"lineNumber":21,"author":{"gitId":"-"},"content":"    public static void main(String[] args) {","lastModifiedDate":"2019-07-29"},{"lineNumber":22,"author":{"gitId":"wonyeji"},"content":"        System.out.println(\"Hello! I\u0027m Jacky\\nWhat can I do for you?\");","lastModifiedDate":"2021-08-19"},{"lineNumber":23,"author":{"gitId":"wonyeji"},"content":"        Scanner sc \u003d new Scanner(System.in);","lastModifiedDate":"2021-08-19"},{"lineNumber":24,"author":{"gitId":"wonyeji"},"content":"        String input \u003d sc.nextLine();","lastModifiedDate":"2021-08-19"},{"lineNumber":25,"author":{"gitId":"wonyeji"},"content":"        while (!input.equals(\"bye\")) {","lastModifiedDate":"2021-08-19"},{"lineNumber":26,"author":{"gitId":"wonyeji"},"content":"            if (input.equals(\"list\")) {","lastModifiedDate":"2021-08-19"},{"lineNumber":27,"author":{"gitId":"wonyeji"},"content":"                printList();","lastModifiedDate":"2021-08-19"},{"lineNumber":28,"author":{"gitId":"wonyeji"},"content":"                input \u003d sc.nextLine();","lastModifiedDate":"2021-08-19"},{"lineNumber":29,"author":{"gitId":"wonyeji"},"content":"                continue;","lastModifiedDate":"2021-08-19"},{"lineNumber":30,"author":{"gitId":"wonyeji"},"content":"            } else if (input.contains(\"done\")) {","lastModifiedDate":"2021-08-19"},{"lineNumber":31,"author":{"gitId":"wonyeji"},"content":"                System.out.println(\"Nice! I\u0027ve marked this task as done: \");","lastModifiedDate":"2021-08-19"},{"lineNumber":32,"author":{"gitId":"wonyeji"},"content":"                int taskNo \u003d Integer.parseInt(input.substring(5));","lastModifiedDate":"2021-08-19"},{"lineNumber":33,"author":{"gitId":"wonyeji"},"content":"                Task task \u003d list.get(taskNo - 1);","lastModifiedDate":"2021-08-19"},{"lineNumber":34,"author":{"gitId":"wonyeji"},"content":"                task.markAsDone();","lastModifiedDate":"2021-08-19"},{"lineNumber":35,"author":{"gitId":"wonyeji"},"content":"                System.out.println(task);","lastModifiedDate":"2021-08-19"},{"lineNumber":36,"author":{"gitId":"wonyeji"},"content":"                input \u003d sc.nextLine();","lastModifiedDate":"2021-08-19"},{"lineNumber":37,"author":{"gitId":"wonyeji"},"content":"                continue;","lastModifiedDate":"2021-08-19"},{"lineNumber":38,"author":{"gitId":"wonyeji"},"content":"            } else if (input.contains(\"delete\")) {","lastModifiedDate":"2021-08-19"},{"lineNumber":39,"author":{"gitId":"wonyeji"},"content":"                System.out.println(\"Noted. I\u0027ve removed this task: \");","lastModifiedDate":"2021-08-19"},{"lineNumber":40,"author":{"gitId":"wonyeji"},"content":"                int taskNo \u003d Integer.parseInt(input.substring(7));","lastModifiedDate":"2021-08-19"},{"lineNumber":41,"author":{"gitId":"wonyeji"},"content":"                Task task \u003d list.get(taskNo - 1);","lastModifiedDate":"2021-08-19"},{"lineNumber":42,"author":{"gitId":"wonyeji"},"content":"                list.remove(taskNo - 1);","lastModifiedDate":"2021-08-19"},{"lineNumber":43,"author":{"gitId":"wonyeji"},"content":"                System.out.println(task);","lastModifiedDate":"2021-08-19"},{"lineNumber":44,"author":{"gitId":"wonyeji"},"content":"                printNoOfTasks();","lastModifiedDate":"2021-08-19"},{"lineNumber":45,"author":{"gitId":"wonyeji"},"content":"                input \u003d sc.nextLine();","lastModifiedDate":"2021-08-19"},{"lineNumber":46,"author":{"gitId":"wonyeji"},"content":"                continue;","lastModifiedDate":"2021-08-19"},{"lineNumber":47,"author":{"gitId":"wonyeji"},"content":"            } else if (input.contains(\"todo\")) {","lastModifiedDate":"2021-08-19"},{"lineNumber":48,"author":{"gitId":"wonyeji"},"content":"                if (input.length() \u003c 6) {","lastModifiedDate":"2021-08-19"},{"lineNumber":49,"author":{"gitId":"wonyeji"},"content":"                    System.out.println(dukeExp.toDo());","lastModifiedDate":"2021-08-19"},{"lineNumber":50,"author":{"gitId":"wonyeji"},"content":"                } else {","lastModifiedDate":"2021-08-19"},{"lineNumber":51,"author":{"gitId":"wonyeji"},"content":"                    ToDo toDo \u003d new ToDo(input.substring(5));","lastModifiedDate":"2021-08-19"},{"lineNumber":52,"author":{"gitId":"wonyeji"},"content":"                    list.add(toDo);","lastModifiedDate":"2021-08-19"},{"lineNumber":53,"author":{"gitId":"wonyeji"},"content":"                    System.out.println(\"Got it. I\u0027ve added this task:\\n\" + toDo.toString());","lastModifiedDate":"2021-08-19"},{"lineNumber":54,"author":{"gitId":"wonyeji"},"content":"                    printNoOfTasks();","lastModifiedDate":"2021-08-19"},{"lineNumber":55,"author":{"gitId":"wonyeji"},"content":"                }","lastModifiedDate":"2021-08-19"},{"lineNumber":56,"author":{"gitId":"wonyeji"},"content":"                input \u003d sc.nextLine();","lastModifiedDate":"2021-08-19"},{"lineNumber":57,"author":{"gitId":"wonyeji"},"content":"                continue;","lastModifiedDate":"2021-08-19"},{"lineNumber":58,"author":{"gitId":"wonyeji"},"content":"            } else if (input.contains(\"deadline\")) {","lastModifiedDate":"2021-08-19"},{"lineNumber":59,"author":{"gitId":"wonyeji"},"content":"//                if (input.length() \u003c 10) {","lastModifiedDate":"2021-08-19"},{"lineNumber":60,"author":{"gitId":"wonyeji"},"content":"//                    System.out.println(dukeExp.deadline() todos","lastModifiedDate":"2021-08-19"},{"lineNumber":61,"author":{"gitId":"wonyeji"},"content":"//                } else {","lastModifiedDate":"2021-08-19"},{"lineNumber":62,"author":{"gitId":"wonyeji"},"content":"                    String[] split \u003d input.split(\"/\");","lastModifiedDate":"2021-08-19"},{"lineNumber":63,"author":{"gitId":"wonyeji"},"content":"                    Deadline deadline \u003d new Deadline(split[0].substring(9), split[1].substring(3));","lastModifiedDate":"2021-08-19"},{"lineNumber":64,"author":{"gitId":"wonyeji"},"content":"                    list.add(deadline);","lastModifiedDate":"2021-08-19"},{"lineNumber":65,"author":{"gitId":"wonyeji"},"content":"                    System.out.println(\"Got it. I\u0027ve added this task:\\n\" + deadline.toString());","lastModifiedDate":"2021-08-19"},{"lineNumber":66,"author":{"gitId":"wonyeji"},"content":"                    printNoOfTasks();","lastModifiedDate":"2021-08-19"},{"lineNumber":67,"author":{"gitId":"wonyeji"},"content":"//                }","lastModifiedDate":"2021-08-19"},{"lineNumber":68,"author":{"gitId":"wonyeji"},"content":"                input \u003d sc.nextLine();","lastModifiedDate":"2021-08-19"},{"lineNumber":69,"author":{"gitId":"wonyeji"},"content":"                continue;","lastModifiedDate":"2021-08-19"},{"lineNumber":70,"author":{"gitId":"wonyeji"},"content":"            } else if (input.contains(\"event\")) {","lastModifiedDate":"2021-08-19"},{"lineNumber":71,"author":{"gitId":"wonyeji"},"content":"//                if (input.length() \u003c 7) {","lastModifiedDate":"2021-08-19"},{"lineNumber":72,"author":{"gitId":"wonyeji"},"content":"//                    System.out.println(dukeExp.event());","lastModifiedDate":"2021-08-19"},{"lineNumber":73,"author":{"gitId":"wonyeji"},"content":"//                } else {","lastModifiedDate":"2021-08-19"},{"lineNumber":74,"author":{"gitId":"wonyeji"},"content":"                    String[] split \u003d input.split(\"/\");","lastModifiedDate":"2021-08-19"},{"lineNumber":75,"author":{"gitId":"wonyeji"},"content":"                    Event event \u003d new Event(split[0].substring(6), split[1].substring(3));","lastModifiedDate":"2021-08-19"},{"lineNumber":76,"author":{"gitId":"wonyeji"},"content":"                    list.add(event);","lastModifiedDate":"2021-08-19"},{"lineNumber":77,"author":{"gitId":"wonyeji"},"content":"                    System.out.println(\"Got it. I\u0027ve added this task:\\n\" + event.toString());","lastModifiedDate":"2021-08-19"},{"lineNumber":78,"author":{"gitId":"wonyeji"},"content":"                    printNoOfTasks();","lastModifiedDate":"2021-08-19"},{"lineNumber":79,"author":{"gitId":"wonyeji"},"content":"//                }","lastModifiedDate":"2021-08-19"},{"lineNumber":80,"author":{"gitId":"wonyeji"},"content":"                input \u003d sc.nextLine();","lastModifiedDate":"2021-08-19"},{"lineNumber":81,"author":{"gitId":"wonyeji"},"content":"                continue;","lastModifiedDate":"2021-08-19"},{"lineNumber":82,"author":{"gitId":"wonyeji"},"content":"            } else {","lastModifiedDate":"2021-08-19"},{"lineNumber":83,"author":{"gitId":"wonyeji"},"content":"                System.out.println(dukeExp.random());","lastModifiedDate":"2021-08-19"},{"lineNumber":84,"author":{"gitId":"wonyeji"},"content":"                input \u003d sc.nextLine();","lastModifiedDate":"2021-08-19"},{"lineNumber":85,"author":{"gitId":"wonyeji"},"content":"                continue;","lastModifiedDate":"2021-08-19"},{"lineNumber":86,"author":{"gitId":"wonyeji"},"content":"            }","lastModifiedDate":"2021-08-19"},{"lineNumber":87,"author":{"gitId":"wonyeji"},"content":"","lastModifiedDate":"2021-08-19"},{"lineNumber":88,"author":{"gitId":"wonyeji"},"content":"        }","lastModifiedDate":"2021-08-19"},{"lineNumber":89,"author":{"gitId":"wonyeji"},"content":"        System.out.println(\"Bye. Hope to see you again soon!\");","lastModifiedDate":"2021-08-19"},{"lineNumber":90,"author":{"gitId":"wonyeji"},"content":"        System.exit(0);","lastModifiedDate":"2021-08-19"},{"lineNumber":91,"author":{"gitId":"-"},"content":"    }","lastModifiedDate":"2019-07-29"},{"lineNumber":92,"author":{"gitId":"-"},"content":"}","lastModifiedDate":"2019-07-29"}],"authorContributionMap":{"wonyeji":88,"-":4}},{"path":"src/main/java/DukeException.java","fileType":"java","lines":[{"lineNumber":1,"author":{"gitId":"wonyeji"},"content":"public class DukeException {","lastModifiedDate":"2021-08-19"},{"lineNumber":2,"author":{"gitId":"wonyeji"},"content":"    private String toDoError \u003d \"☹ OOPS!!! The description of a todo cannot be empty.\";","lastModifiedDate":"2021-08-19"},{"lineNumber":3,"author":{"gitId":"wonyeji"},"content":"    private String randomError \u003d \"☹ OOPS!!! I\u0027m sorry, but I don\u0027t know what that means :-(\";","lastModifiedDate":"2021-08-19"},{"lineNumber":4,"author":{"gitId":"wonyeji"},"content":"    private String deadlineError \u003d \"☹ OOPS!!! Please indicate a valid deadline.\";","lastModifiedDate":"2021-08-19"},{"lineNumber":5,"author":{"gitId":"wonyeji"},"content":"    private String eventError \u003d \"☹ OOPS!!! Please indicate a valid event date.\";","lastModifiedDate":"2021-08-19"},{"lineNumber":6,"author":{"gitId":"wonyeji"},"content":"","lastModifiedDate":"2021-08-19"},{"lineNumber":7,"author":{"gitId":"wonyeji"},"content":"    public String toDo() {","lastModifiedDate":"2021-08-19"},{"lineNumber":8,"author":{"gitId":"wonyeji"},"content":"        return toDoError;","lastModifiedDate":"2021-08-19"},{"lineNumber":9,"author":{"gitId":"wonyeji"},"content":"    }","lastModifiedDate":"2021-08-19"},{"lineNumber":10,"author":{"gitId":"wonyeji"},"content":"","lastModifiedDate":"2021-08-19"},{"lineNumber":11,"author":{"gitId":"wonyeji"},"content":"    public String random() {","lastModifiedDate":"2021-08-19"},{"lineNumber":12,"author":{"gitId":"wonyeji"},"content":"        return randomError;","lastModifiedDate":"2021-08-19"},{"lineNumber":13,"author":{"gitId":"wonyeji"},"content":"    }","lastModifiedDate":"2021-08-19"},{"lineNumber":14,"author":{"gitId":"wonyeji"},"content":"","lastModifiedDate":"2021-08-19"},{"lineNumber":15,"author":{"gitId":"wonyeji"},"content":"    public String deadline() {","lastModifiedDate":"2021-08-19"},{"lineNumber":16,"author":{"gitId":"wonyeji"},"content":"        return deadlineError;","lastModifiedDate":"2021-08-19"},{"lineNumber":17,"author":{"gitId":"wonyeji"},"content":"    }","lastModifiedDate":"2021-08-19"},{"lineNumber":18,"author":{"gitId":"wonyeji"},"content":"","lastModifiedDate":"2021-08-19"},{"lineNumber":19,"author":{"gitId":"wonyeji"},"content":"    public String event() {","lastModifiedDate":"2021-08-19"},{"lineNumber":20,"author":{"gitId":"wonyeji"},"content":"        return eventError;","lastModifiedDate":"2021-08-19"},{"lineNumber":21,"author":{"gitId":"wonyeji"},"content":"    }","lastModifiedDate":"2021-08-19"},{"lineNumber":22,"author":{"gitId":"wonyeji"},"content":"}","lastModifiedDate":"2021-08-19"}],"authorContributionMap":{"wonyeji":22}},{"path":"src/main/java/Event.java","fileType":"java","lines":[{"lineNumber":1,"author":{"gitId":"wonyeji"},"content":"public class Event extends Task {","lastModifiedDate":"2021-08-19"},{"lineNumber":2,"author":{"gitId":"wonyeji"},"content":"","lastModifiedDate":"2021-08-19"},{"lineNumber":3,"author":{"gitId":"wonyeji"},"content":"    protected String at;","lastModifiedDate":"2021-08-19"},{"lineNumber":4,"author":{"gitId":"wonyeji"},"content":"","lastModifiedDate":"2021-08-19"},{"lineNumber":5,"author":{"gitId":"wonyeji"},"content":"    public Event(String description, String at) {","lastModifiedDate":"2021-08-19"},{"lineNumber":6,"author":{"gitId":"wonyeji"},"content":"        super(description);","lastModifiedDate":"2021-08-19"},{"lineNumber":7,"author":{"gitId":"wonyeji"},"content":"        this.at \u003d at;","lastModifiedDate":"2021-08-19"},{"lineNumber":8,"author":{"gitId":"wonyeji"},"content":"    }","lastModifiedDate":"2021-08-19"},{"lineNumber":9,"author":{"gitId":"wonyeji"},"content":"","lastModifiedDate":"2021-08-19"},{"lineNumber":10,"author":{"gitId":"wonyeji"},"content":"    @Override","lastModifiedDate":"2021-08-19"},{"lineNumber":11,"author":{"gitId":"wonyeji"},"content":"    public String toString() {","lastModifiedDate":"2021-08-19"},{"lineNumber":12,"author":{"gitId":"wonyeji"},"content":"        return \"[E]\" + super.toString() + \" (at: \" + at + \")\";","lastModifiedDate":"2021-08-19"},{"lineNumber":13,"author":{"gitId":"wonyeji"},"content":"    }","lastModifiedDate":"2021-08-19"},{"lineNumber":14,"author":{"gitId":"wonyeji"},"content":"}","lastModifiedDate":"2021-08-19"}],"authorContributionMap":{"wonyeji":14}},{"path":"src/main/java/Task.java","fileType":"java","lines":[{"lineNumber":1,"author":{"gitId":"wonyeji"},"content":"public class Task {","lastModifiedDate":"2021-08-19"},{"lineNumber":2,"author":{"gitId":"wonyeji"},"content":"    protected String description;","lastModifiedDate":"2021-08-19"},{"lineNumber":3,"author":{"gitId":"wonyeji"},"content":"    protected boolean isDone;","lastModifiedDate":"2021-08-19"},{"lineNumber":4,"author":{"gitId":"wonyeji"},"content":"","lastModifiedDate":"2021-08-19"},{"lineNumber":5,"author":{"gitId":"wonyeji"},"content":"    public Task(String description) {","lastModifiedDate":"2021-08-19"},{"lineNumber":6,"author":{"gitId":"wonyeji"},"content":"        this.description \u003d description;","lastModifiedDate":"2021-08-19"},{"lineNumber":7,"author":{"gitId":"wonyeji"},"content":"        this.isDone \u003d false;","lastModifiedDate":"2021-08-19"},{"lineNumber":8,"author":{"gitId":"wonyeji"},"content":"    }","lastModifiedDate":"2021-08-19"},{"lineNumber":9,"author":{"gitId":"wonyeji"},"content":"","lastModifiedDate":"2021-08-19"},{"lineNumber":10,"author":{"gitId":"wonyeji"},"content":"    public String getStatusIcon() {","lastModifiedDate":"2021-08-19"},{"lineNumber":11,"author":{"gitId":"wonyeji"},"content":"        return (isDone ? \"X\" : \" \"); // mark done task with X","lastModifiedDate":"2021-08-19"},{"lineNumber":12,"author":{"gitId":"wonyeji"},"content":"    }","lastModifiedDate":"2021-08-19"},{"lineNumber":13,"author":{"gitId":"wonyeji"},"content":"","lastModifiedDate":"2021-08-19"},{"lineNumber":14,"author":{"gitId":"wonyeji"},"content":"    public void markAsDone() {","lastModifiedDate":"2021-08-19"},{"lineNumber":15,"author":{"gitId":"wonyeji"},"content":"        isDone \u003d true;","lastModifiedDate":"2021-08-19"},{"lineNumber":16,"author":{"gitId":"wonyeji"},"content":"    }","lastModifiedDate":"2021-08-19"},{"lineNumber":17,"author":{"gitId":"wonyeji"},"content":"","lastModifiedDate":"2021-08-19"},{"lineNumber":18,"author":{"gitId":"wonyeji"},"content":"    @Override","lastModifiedDate":"2021-08-19"},{"lineNumber":19,"author":{"gitId":"wonyeji"},"content":"    public String toString() {","lastModifiedDate":"2021-08-19"},{"lineNumber":20,"author":{"gitId":"wonyeji"},"content":"        return \"[\" + getStatusIcon() + \"] \" + description;","lastModifiedDate":"2021-08-19"},{"lineNumber":21,"author":{"gitId":"wonyeji"},"content":"    }","lastModifiedDate":"2021-08-19"},{"lineNumber":22,"author":{"gitId":"wonyeji"},"content":"}","lastModifiedDate":"2021-08-19"}],"authorContributionMap":{"wonyeji":22}},{"path":"src/main/java/ToDo.java","fileType":"java","lines":[{"lineNumber":1,"author":{"gitId":"wonyeji"},"content":"public class ToDo extends Task {","lastModifiedDate":"2021-08-19"},{"lineNumber":2,"author":{"gitId":"wonyeji"},"content":"","lastModifiedDate":"2021-08-19"},{"lineNumber":3,"author":{"gitId":"wonyeji"},"content":"    public ToDo(String description) {","lastModifiedDate":"2021-08-19"},{"lineNumber":4,"author":{"gitId":"wonyeji"},"content":"        super(description);","lastModifiedDate":"2021-08-19"},{"lineNumber":5,"author":{"gitId":"wonyeji"},"content":"    }","lastModifiedDate":"2021-08-19"},{"lineNumber":6,"author":{"gitId":"wonyeji"},"content":"","lastModifiedDate":"2021-08-19"},{"lineNumber":7,"author":{"gitId":"wonyeji"},"content":"    @Override","lastModifiedDate":"2021-08-19"},{"lineNumber":8,"author":{"gitId":"wonyeji"},"content":"    public String toString() {","lastModifiedDate":"2021-08-19"},{"lineNumber":9,"author":{"gitId":"wonyeji"},"content":"        return \"[T]\" + super.toString();","lastModifiedDate":"2021-08-19"},{"lineNumber":10,"author":{"gitId":"wonyeji"},"content":"    }","lastModifiedDate":"2021-08-19"},{"lineNumber":11,"author":{"gitId":"wonyeji"},"content":"}","lastModifiedDate":"2021-08-19"}],"authorContributionMap":{"wonyeji":11}}]
